hmmm.sv
/* verilator lint_off CASEOVERLAP */
/* verilator lint_off DECLFILENAME */
/* verilator lint_off UNUSEDSIGNAL */
/* verilator lint_off CASEINCOMPLETE */

typedef enum {
  HALT,
  NOP,
  READ,
  WRITE,
  SETN,
  LOADR,
  STORER,
  POPR,
  PUSHR,
  LOADN,
  STOREN,
  ADDN,
  ADD,
  COPY,
  SUB,
  NEG,
  MUL,
  DIV,
  MOD,
  JUMPR,
  JUMPN,
  JEQZN,
  JNEZN,
  JGTZN,
  JLTZN,
  CALLN
} instr_t;

typedef enum {
  ALU_ADD,
  ALU_SUB,
  ALU_MUL,
  ALU_DIV,
  ALU_MOD
} alu_op_t;


module hmmm (
    input logic clk,
    reset
);
  logic [15:0] instruction;
  logic [1:0] rf_src_x, pc_src, mem_adr_src, alu_src_b;
  logic mem_write, rf_write_en_x, rf_write_en_y, mem_data_src, alu_src_a;

  alu_op_t alu_op;
  instr_t  instruction_type;

  Controller controller (
      .instruction(instruction),
      .alu_op(alu_op),
      .alu_src_a(alu_src_a),
      .alu_src_b(alu_src_b),
      .mem_write(mem_write),
      .rf_write_en_x(rf_write_en_x),
      .rf_src_x(rf_src_x),
      .rf_write_en_y(rf_write_en_y),
      .mem_adr_src(mem_adr_src),
      .mem_data_src(mem_data_src),
      .pc_src(pc_src),
      .instruction_type(instruction_type)
  );

  Datapath datapath (
      .clk(clk),
      .reset(reset),
      .mem_write(mem_write),
      .rf_write_en_x(rf_write_en_x),
      .rf_src_x(rf_src_x),
      .rf_write_en_y(rf_write_en_y),
      .mem_adr_src(mem_adr_src),
      .mem_data_src(mem_data_src),
      .pc_src(pc_src),
      .alu_op(alu_op),
      .alu_src_a(alu_src_a),
      .alu_src_b(alu_src_b),
      .instruction_type(instruction_type),
      .instruction(instruction)
  );
endmodule

module Memory (
    input logic clk,
    mem_write_en,
    input logic [7:0] pc,
    mem_data_address,
    input logic [15:0] mem_write_data,
    output logic [15:0] instruction,
    mem_read_data
);
  initial $readmemb("program.txt", RAM);

  logic [15:0] RAM[255:0];

  always_ff @(posedge clk) if (mem_write_en) RAM[mem_data_address] <= mem_write_data;

  assign instruction   = RAM[{1'b0, pc[7:1]}];  // needs to be word-aligned to 2 bytes TODO check
  assign mem_read_data = RAM[mem_data_address];
endmodule

module RegisterFile (
    input logic clk,
    input logic [3:0] rf_adr_x,
    rf_adr_y,
    rf_adr_z,
    input logic rf_write_en_x,
    rf_write_en_y,
    input logic [15:0] rf_write_data_x,
    rf_write_data_y,
    output logic [15:0] rf_read_data_x,
    rf_read_data_y,
    rf_read_data_z
);

  // TODO pretty sure we are allocating flops for r0 needlessly
  logic [15:0] registers[15:0];

  assign rf_read_data_x = (rf_adr_x != 0) ? registers[rf_adr_x] : 16'd0;
  assign rf_read_data_y = (rf_adr_y != 0) ? registers[rf_adr_y] : 16'd0;
  assign rf_read_data_z = (rf_adr_z != 0) ? registers[rf_adr_z] : 16'd0;

  always_ff @(posedge clk) begin
    if (rf_write_en_x & rf_write_en_y & (rf_adr_x == rf_adr_y))
      $display(
          "WARNING: write to same register in same cycle. Second write channel takes priority."
      );
    if (rf_write_en_x) registers[rf_adr_x] = rf_write_data_x;
    if (rf_write_en_y) registers[rf_adr_y] = rf_write_data_y;
  end
endmodule

module Controller (
    input logic [15:0] instruction,
    output alu_op_t alu_op,
    output logic mem_write,
    rf_write_en_x,
    rf_write_en_y,
    mem_data_src,
    alu_src_a,
    output logic [1:0] rf_src_x,
    alu_src_b,
    mem_adr_src,
    pc_src,
    output instr_t instruction_type
);


  always_comb
    casez (instruction)

      // CONTROL_FLOW
      16'b0000_0000_0000_0000: instruction_type = HALT;

      16'b0000_????_0000_0001: instruction_type = READ;  // todo no great way to do in hardware

      16'b0000_????_0000_0010: instruction_type = WRITE;
      16'b0000_????_0000_0011: instruction_type = JUMPR;

      // SETN
      16'b0001_????_????_????: instruction_type = SETN;

      // LOADN
      16'b0010_????_????_????: instruction_type = LOADN;

      // STOREN
      16'b0011_????_????_????: instruction_type = STOREN;


      // MEMORY_R
      16'b0100_????_????_0000: instruction_type = LOADR;
      16'b0100_????_????_0001: instruction_type = STORER;

      16'b0100_????_????_0010: instruction_type = POPR;
      16'b0100_????_????_0011: instruction_type = PUSHR;

      // ADDN
      16'b0101_????_????_????: instruction_type = ADDN;

      // ADD
      16'b0110_????_????_????: instruction_type = ADD;
      // 16'b0110_0000_0000_0000: instruction_type = NOP; // add duplicate, covered as the default case
      16'b0110_????_????_0000: instruction_type = COPY;

      // SUB
      16'b0111_????_????_????: instruction_type = SUB;
      16'b0111_????_0000_????: instruction_type = NEG;  // sub duplicate

      // Mul
      16'b1000_????_????_????: instruction_type = MUL;

      // Div
      16'b1001_????_????_????: instruction_type = DIV;

      // Mod
      16'b1010_????_????_????: instruction_type = MOD;

      // JUMPN_CALLN
      16'b1011_0000_????_????: instruction_type = JUMPN;
      16'b1011_????_????_????: instruction_type = CALLN;


      // Conditional jumps

      16'b1100_????_????_????: instruction_type = JEQZN;

      16'b1101_????_????_????: instruction_type = JNEZN;

      16'b1110_????_????_????: instruction_type = JGTZN;

      16'b1111_????_????_????: instruction_type = JLTZN;
      default: begin
        $display("unknown instruction, defaulting to NOP");
        instruction_type = NOP;
      end
    endcase

  // rf_src_x:
  //	 00: from immediate
  //	 01: from data memory (data read)
  //	 10: from pc + 2 (next instruction w/o jump)
  //	 11: from ALU result
  //
  //
  // mem_adr_src:
  //   00: from immediate
  //   01: from register file (data read 2, rf_adr_y) 
  //   10: from alu_result
  //
  // pc_src:
  //    00: from pc + 2
  //    10: from pc_target (immediate)
  //    11: from pc_target (rf_adr_x)
  //
  //  mem_data_src: 
  //    0: from ALU result
  //    1: from register file (data read 1, rf_adr_x) 
  //
  //  alu_src_a:
  //    0: from register file (data read 2, rf_adr_y)
  //    1: from register file (data read 1, rf_adr_x)
  //
  //  alu_src_b: 
  //    00: from register file (data read 3, rf_adr_z)
  //    01: from immediate
  //    10: from 0
  //    11: from 1


  always_comb begin
    // defaults
    mem_adr_src = 2'b0;  // memory sources from immediate
    mem_data_src = 0;  // memory gets write data from ALU result
    mem_write = 0;  // disable write to memory
    pc_src = 2'b00;  // pc gets pc + 2
    rf_src_x = 2'b00;  // register file gets write data from immediate
    rf_write_en_x = 0;  // disable write to register file
    alu_op = ALU_ADD;  // default ALU operation is ADD
    alu_src_a = 0;  // default ALU source A is the contents of register rf_adr_x
    alu_src_b = 2'b00;  // default ALU source B is the contents of register rf_adr_y

    $display("\n");
    case (instruction_type)
      LOADR: begin
        $display("LOADR");
        // Load register rf_adr_x with data from the address location held in reg. rf_adr_y
        mem_adr_src = 2'b1;  // get the memory from address valued rf_adr_y
        rf_src_x = 2'b01;  // direct data from memory to rf_adr_x
        rf_write_en_x = 1;  // enable write to rx
      end
      READ: begin
        $display("READ");
        // emulator, read from stdin, processor, read from 16 bit input (presumed to be hooked up to serial transfer peripheral)
        // Ideally, should stall the processor until the input is ready.
        // TODO 
        $display("WARNING: READ unimplemented.");
      end
      WRITE: begin
        $display("WRITE");
        // Print contents of register rf_adr_x
        // rf_adr_x is already hard-wired into the first address port of the register file
        // so we will simply print from the corresponding read_data_1 output
      end
      SETN: begin
        $display("SETN");
        // Set register rf_adr_x equal to the integer N (-128 to +127)
        rf_src_x   = 2'b00;  // direct the immediate to rf_adr_x
        rf_write_en_x = 1;  // enable write to rx
      end
      LOADN: begin
        $display("LOADN");
        // Load register rf_adr_x with the contents of memory address N
        mem_adr_src = 2'b0;  // get the memory at the address corresponding to the immediate
        rf_src_x = 2'b01;  // direct data from memory to rf_adr_x
        rf_write_en_x = 1;  // enable write to rx
      end
      JUMPN: begin
        // Set program counter to address N
        $display("JUMPN");
        pc_src = 2'b10;  // get the next program counter from the immediate
      end
      JUMPR: begin
        $display("JUMPR");
        //Set program counter to address in rf_adr_x
        pc_src = 2'b11;  // get the next program counter from the contents of rf_adr_x
      end
      JEQZN: begin
        $display("JEQZN");
        pc_src = 2'b10;  // next program counter is sourced from the immediate (provided rf_adr_x satisfies the condition)

      end
      JNEZN: begin
        $display("JNEZN");
        pc_src = 2'b10;  // next program counter is sourced from the immediate (provided rf_adr_x satisfies the condition)
      end
      JGTZN: begin
        $display("JGTZN");
        pc_src = 2'b10;  // next program counter is sourced from the immediate (provided rf_adr_x satisfies the condition)
      end
      JLTZN: begin
        $display("JLTZN");
        pc_src = 2'b10;  // next program counter is sourced from the immediate (provided rf_adr_x satisfies the condition)
      end
      CALLN: begin
        $display("CALLN");
        // Copy addr. of next instr. into rf_adr_x and then jump to mem. addr. N
        pc_src = 2'b10;  // next program counter is sourced from the immediate
        rf_src_x = 2'b10; // save the instruction address immediately following the CALLN instruction into rf_adr_x
        rf_write_en_x = 1;  // enable write to rf_adr_x
      end
      STOREN: begin
        $display("STOREN");
        // Store contents of register rf_adr_x into memory address N
        mem_adr_src = 2'b00;  // direct the immediate to the memory address
        mem_data_src = 1;  // direct rf_adr_x to the memory data input
        mem_write = 1;  // enable write to memory
      end
      STORER: begin
        $display("STORER");
        // Store contents of register rf_adr_x into memory address held in reg. rf_adr_y
        mem_data_src = 1;  // get data from rf_adr_x
        mem_adr_src = 2'b01;  // direct to address at rf_adr_y
        mem_write = 1;  // enable write to memory
      end
      POPR: begin
        $display("POPR");
        // Load contents of register rf_adr_x from stack pointed to by register rf_adr_y: rf_adr_y -= 1; rf_adr_x = memory[rf_adr_y]

        // alu_result = rf_adr_y - 1
        alu_src_a = 0;  // rf_adr_y
        alu_src_b = 2'b11;  // 1
        alu_op = ALU_SUB;  // sub

        // rf_adr_y = alu_result
        rf_write_en_y = 1;  // enable write to rf_adr_y (default source from alu_result)

        // rf_adr_x = memory[rf_adr_y]
        mem_adr_src = 2'b10;  // get the data at the address corresponding to old rf_adr_y + 1 (alu_result)
        rf_src_x = 2'b01;  // direct the memory data to rf_adr_x
        rf_write_en_x = 1;  // enable write to rf_adr_x

      end
      PUSHR: begin
        $display("PUSHR");
        // Store contents of register rf_adr_x onto stack pointed to by register rf_adr_y: memory[rf_adr_y] = rf_adr_x; rf_adr_y += 1
        // 
        mem_data_src = 1;  // direct the contents of rf_adr_x to the memory
        mem_adr_src = 2'b01;  // write to memory address rf_adr_y
        mem_write = 1;  // enable write to memory

        // alu_result = rf_adr_y + 1
        alu_src_a = 0;  // rf_adr_y
        alu_src_b = 2'b11;  // 1
        alu_op = ALU_ADD;  // add

        // rf_adr_y = alu_result
        rf_write_en_y = 1;  // enable write to rf_adr_y (default source from alu_result)
      end
      ADD, COPY, NOP: begin
        case (instruction_type)
          ADD: $display("ADD");
          COPY:
          $display(
              "COPY"
          );  // COPY is the case of ADD where sources b from r0, which is hard-wired to 0
          NOP:
          $display(
              "NOP"
          );  // NOP is the case of ADD where a, b, and result are all from/to r0, which is hard-wired to 0
        endcase
        // alu_result = rf_adr_y + rf_adr_z
        alu_src_a = 0;  // rf_adr_y
        alu_src_b = 2'b00;  // rf_adr_z
        alu_op = ALU_ADD;

        // rf_adr_x = alu_result
        rf_src_x = 2'b11;  // register file gets write data from the ALU result
        rf_write_en_x = 1;  // enable write to rx
      end
      ADDN: begin  // Copy is a duplicate of ADD which always gets 
        $display("ADDN");  // todo check
        // alu_result = rf_adr_x + N
        alu_src_a = 1;  // rf_adr_x
        alu_src_b = 2'b01;  // immediate
        alu_op = ALU_ADD;

        // rf_adr_x = alu_result
        rf_src_x = 2'b11;  // register file gets write data from the ALU result
        rf_write_en_x = 1;  // enable write to rx
      end
      SUB, NEG: begin
        case (instruction_type)
          SUB: $display("SUB");
          NEG:
          $display(
              "NEG"
          );  // NEG is the case of SUB where source a is taken from r0, which is hard-wired to 0
        endcase
        // alu_result = rf_adr_y - rf_adr_z
        alu_src_a = 0;  // rf_adr_y
        alu_src_b = 2'b00;  // rf_adr_z
        alu_op = ALU_SUB;

        // rf_adr_x = alu_result
        rf_src_x = 2'b11;  // register file gets write data from the ALU result
        rf_write_en_x = 1;  // enable write to rx
      end
      MUL: begin
        $display("MUL");
        // alu_result = rf_adr_y * rf_adr_z
        alu_src_a = 0;  // rf_adr_y
        alu_src_b = 2'b00;  // rf_adr_z
        alu_op = ALU_MUL;

        // rf_adr_x = alu_result
        rf_src_x = 2'b11;  // register file gets write data from the ALU result
        rf_write_en_x = 1;  // enable write to rx
      end
      DIV: begin
        $display("DIV");
        // alu_result = rf_adr_y / rf_adr_z
        alu_src_a = 0;  // rf_adr_y
        alu_src_b = 2'b00;  // rf_adr_z
        alu_op = ALU_DIV;

        // rf_adr_x = alu_result
        rf_src_x = 2'b11;  // register file gets write data from the ALU result
        rf_write_en_x = 1;  // enable write to rx
      end
      MOD: begin
        $display("MOD");
        // alu_result = rf_adr_y % rf_adr_z
        alu_src_a = 0;  // rf_adr_y
        alu_src_b = 2'b00;  // rf_adr_z
        alu_op = ALU_MOD;

        // rf_adr_x = alu_result
        rf_src_x = 2'b11;  // register file gets write data from the ALU result
        rf_write_en_x = 1;  // enable write to rx
      end
    endcase
  end



endmodule

module Datapath (
    input logic clk,
    reset,
    input logic mem_write,
    rf_write_en_x,
    rf_write_en_y,
    mem_data_src,
    alu_src_a,
    input logic [1:0] pc_src,
    alu_src_b,
    rf_src_x,
    mem_adr_src,
    input instr_t instruction_type,
    input alu_op_t alu_op,
    output logic [15:0] instruction
);

  // ==============  Internal Signals ============== 


  logic [7:0] pc, pc_plus_2, pc_next, pc_target, immediate, mem_data_address;

  logic [15:0]
      result,
      alu_result,
      alu_input_a,
      alu_input_b,
      rf_read_data_x,
      rf_read_data_y,
      rf_read_data_z,
      rf_write_data_x,
      rf_write_data_y,
      mem_read_data,
      mem_write_data;

  logic [3:0] rf_adr_x, rf_adr_y, rf_adr_z;

  assign rf_adr_x = instruction[11:8];
  assign rf_adr_y = instruction[7:4];
  assign rf_adr_z = instruction[3:0];
  assign immediate = instruction[7:0];

  logic zero, sign;


  // ============== pc logic ============== 
  always_ff @(posedge clk) pc <= pc_next;

  assign zero = (rf_read_data_x == 0);
  assign sign = rf_read_data_x[15];

  logic take_jump;

  always_comb
    case (instruction_type)
      JEQZN:   take_jump = zero;
      JNEZN:   take_jump = ~zero;
      JGTZN:   take_jump = ~sign & ~zero;
      JLTZN:   take_jump = sign;
      JUMPR:   take_jump = 1;
      JUMPN:   take_jump = 1;
      default: take_jump = 1;
    endcase

  always_comb
    if (reset) pc_next = 0;
    else if (pc_src[1] & take_jump) pc_next = pc_target;
    else pc_next = pc_plus_2;  // word alignment is 2 bytes

  assign pc_target = pc_src[0] ? rf_read_data_x[7:0] : immediate << 1;  // todo check
  assign pc_plus_2 = pc + 2;


  // cheat to handle status prints, write and halt

  always_ff @(posedge clk) begin
    $display("Instruction number: %d", pc / 2);
    $display("instruction: %h", instruction);

    if (instruction_type == WRITE) $display("write: %b", rf_read_data_x);
    else if (instruction_type == HALT) begin
      $display("halt");

      // dump registers
      for (int i = 0; i < 16; i++) begin
        $display("reg[%d]: %h", i, rf.registers[i]);
      end
      $display("\n");
      // dump memory
      for (int i = 0; i < 256; i++) begin
        $display("mem[%d]: %h", i, mem.RAM[i]);
      end
      // done
      $finish;
    end
  end


  // ============== Memory logic ============== 
  Memory mem (
      .clk(clk),
      .mem_write_en(mem_write),
      .pc(pc),
      .mem_data_address(mem_data_address),
      .mem_write_data(mem_write_data),
      .instruction(instruction),
      .mem_read_data(mem_read_data)
  );

  always_comb
    case (mem_adr_src)
      2'b00: mem_data_address = immediate;
      2'b01: mem_data_address = rf_read_data_y[7:0];
      2'b10: mem_data_address = alu_result[7:0];
    endcase

  assign mem_write_data = mem_data_src ? rf_read_data_x : alu_result;

  logic [15:0] imm_ext;
  assign imm_ext = immediate[7] ? {8'b11111111, immediate} : {8'b0, immediate};

  always_comb
    case (rf_src_x)
      2'b00: rf_write_data_x = imm_ext;
      2'b01: rf_write_data_x = mem_read_data;
      2'b10: rf_write_data_x = {8'b0, pc_plus_2};
      2'b11: rf_write_data_x = alu_result;
    endcase

  assign rf_write_data_y = alu_result;

  // ============== REGISTER FILE logic ============== 
  RegisterFile rf (
      .clk(clk),
      .rf_adr_x(rf_adr_x),
      .rf_adr_y(rf_adr_y),
      .rf_adr_z(rf_adr_z),
      .rf_write_en_x(rf_write_en_x),
      .rf_write_en_y(rf_write_en_y),
      .rf_write_data_x(rf_write_data_x),
      .rf_write_data_y(rf_write_data_y),
      .rf_read_data_x(rf_read_data_x),
      .rf_read_data_y(rf_read_data_y),
      .rf_read_data_z(rf_read_data_z)
  );

  // ============= ALU logic ============== 

  ALU alu (
      .alu_op(alu_op),
      .alu_input_a(alu_input_a),
      .alu_input_b(alu_input_b),
      .alu_result(alu_result)
  );

  assign alu_input_a = alu_src_a ? rf_read_data_x : rf_read_data_y;

  always_comb
    case (alu_src_b)
      2'b0:  alu_input_b = rf_read_data_z;
      2'b1:  alu_input_b = imm_ext;
      2'b10: alu_input_b = 0;
      2'b11: alu_input_b = 1;
    endcase
endmodule

module ALU (
    input alu_op_t alu_op,
    input logic [15:0] alu_input_a,
    alu_input_b,
    output logic [15:0] alu_result
);

  always_comb
    case (alu_op)
      ALU_ADD: alu_result = alu_input_a + alu_input_b;
      ALU_SUB: alu_result = alu_input_a - alu_input_b;
      ALU_MUL: alu_result = alu_input_a * alu_input_b;
      ALU_DIV: alu_result = alu_input_a / alu_input_b;  // todo check div by 0
      ALU_MOD: alu_result = alu_input_a % alu_input_b;
    endcase
endmodule

waveform.vcd
$version Generated by VerilatedVcd $end
$timescale 1ps $end

 $scope module TOP $end
  $var wire  1 V clk $end
  $var wire  1 W reset $end
  $scope module hmmm $end
   $var wire 32 - alu_op [31:0] $end
   $var wire  1 , alu_src_a $end
   $var wire  2 ' alu_src_b [1:0] $end
   $var wire  1 V clk $end
   $var wire 16 # instruction [15:0] $end
   $var wire 32 . instruction_type [31:0] $end
   $var wire  2 & mem_adr_src [1:0] $end
   $var wire  1 + mem_data_src $end
   $var wire  1 ( mem_write $end
   $var wire  2 % pc_src [1:0] $end
   $var wire  1 W reset $end
   $var wire  2 $ rf_src_x [1:0] $end
   $var wire  1 ) rf_write_en_x $end
   $var wire  1 * rf_write_en_y $end
   $scope module controller $end
    $var wire 32 - alu_op [31:0] $end
    $var wire  1 , alu_src_a $end
    $var wire  2 ' alu_src_b [1:0] $end
    $var wire 16 # instruction [15:0] $end
    $var wire 32 . instruction_type [31:0] $end
    $var wire  2 & mem_adr_src [1:0] $end
    $var wire  1 + mem_data_src $end
    $var wire  1 ( mem_write $end
    $var wire  2 % pc_src [1:0] $end
    $var wire  2 $ rf_src_x [1:0] $end
    $var wire  1 ) rf_write_en_x $end
    $var wire  1 * rf_write_en_y $end
   $upscope $end
   $scope module datapath $end
    $var wire 16 5 alu_input_a [15:0] $end
    $var wire 16 6 alu_input_b [15:0] $end
    $var wire 32 - alu_op [31:0] $end
    $var wire 16 4 alu_result [15:0] $end
    $var wire  1 , alu_src_a $end
    $var wire  2 ' alu_src_b [1:0] $end
    $var wire  1 V clk $end
    $var wire 16 C imm_ext [15:0] $end
    $var wire  8 2 immediate [7:0] $end
    $var wire 16 # instruction [15:0] $end
    $var wire 32 . instruction_type [31:0] $end
    $var wire  2 & mem_adr_src [1:0] $end
    $var wire  8 3 mem_data_address [7:0] $end
    $var wire  1 + mem_data_src $end
    $var wire 16 ; mem_read_data [15:0] $end
    $var wire  1 ( mem_write $end
    $var wire 16 < mem_write_data [15:0] $end
    $var wire  8 / pc [7:0] $end
    $var wire  8 X pc_next [7:0] $end
    $var wire  8 0 pc_plus_2 [7:0] $end
    $var wire  2 % pc_src [1:0] $end
    $var wire  8 1 pc_target [7:0] $end
    $var wire  1 W reset $end
    $var wire 16 Y result [15:0] $end
    $var wire  4 = rf_adr_x [3:0] $end
    $var wire  4 > rf_adr_y [3:0] $end
    $var wire  4 ? rf_adr_z [3:0] $end
    $var wire 16 7 rf_read_data_x [15:0] $end
    $var wire 16 8 rf_read_data_y [15:0] $end
    $var wire 16 9 rf_read_data_z [15:0] $end
    $var wire  2 $ rf_src_x [1:0] $end
    $var wire 16 : rf_write_data_x [15:0] $end
    $var wire 16 4 rf_write_data_y [15:0] $end
    $var wire  1 ) rf_write_en_x $end
    $var wire  1 * rf_write_en_y $end
    $var wire  1 A sign $end
    $var wire  1 B take_jump $end
    $var wire  1 @ zero $end
    $scope module alu $end
     $var wire 16 5 alu_input_a [15:0] $end
     $var wire 16 6 alu_input_b [15:0] $end
     $var wire 32 - alu_op [31:0] $end
     $var wire 16 4 alu_result [15:0] $end
    $upscope $end
    $scope module mem $end
     $var wire  1 V clk $end
     $var wire 16 # instruction [15:0] $end
     $var wire  8 3 mem_data_address [7:0] $end
     $var wire 16 ; mem_read_data [15:0] $end
     $var wire 16 < mem_write_data [15:0] $end
     $var wire  1 ( mem_write_en $end
     $var wire  8 / pc [7:0] $end
    $upscope $end
    $scope module rf $end
     $var wire  1 V clk $end
     $var wire 16 D registers[0] [15:0] $end
     $var wire 16 N registers[10] [15:0] $end
     $var wire 16 O registers[11] [15:0] $end
     $var wire 16 P registers[12] [15:0] $end
     $var wire 16 Q registers[13] [15:0] $end
     $var wire 16 R registers[14] [15:0] $end
     $var wire 16 S registers[15] [15:0] $end
     $var wire 16 E registers[1] [15:0] $end
     $var wire 16 F registers[2] [15:0] $end
     $var wire 16 G registers[3] [15:0] $end
     $var wire 16 H registers[4] [15:0] $end
     $var wire 16 I registers[5] [15:0] $end
     $var wire 16 J registers[6] [15:0] $end
     $var wire 16 K registers[7] [15:0] $end
     $var wire 16 L registers[8] [15:0] $end
     $var wire 16 M registers[9] [15:0] $end
     $var wire  4 = rf_adr_x [3:0] $end
     $var wire  4 > rf_adr_y [3:0] $end
     $var wire  4 ? rf_adr_z [3:0] $end
     $var wire 16 7 rf_read_data_x [15:0] $end
     $var wire 16 8 rf_read_data_y [15:0] $end
     $var wire 16 9 rf_read_data_z [15:0] $end
     $var wire 16 : rf_write_data_x [15:0] $end
     $var wire 16 4 rf_write_data_y [15:0] $end
     $var wire  1 ) rf_write_en_x $end
     $var wire  1 * rf_write_en_y $end
    $upscope $end
    $scope module unnamedblk1 $end
     $var wire 32 T i [31:0] $end
    $upscope $end
    $scope module unnamedblk2 $end
     $var wire 32 U i [31:0] $end
    $upscope $end
   $upscope $end
  $upscope $end
 $upscope $end
$enddefinitions $end


#0
b0001111000000000 #
b00 $
b00 %
b00 &
b00 '
0(
1)
0*
0+
0,
b00000000000000000000000000000000 -
b00000000000000000000000000000100 .
b00000000 /
b00000010 0
b00000000 1
b00000000 2
b00000000 3
b0000000000000000 4
b0000000000000000 5
b0000000000000000 6
b0000000000000000 7
b0000000000000000 8
b0000000000000000 9
b0000000000000000 :
b0001111000000000 ;
b0000000000000000 <
b1110 =
b0000 >
b0000 ?
1@
0A
1B
b0000000000000000 C
b0000000000000000 D
b0000000000000000 E
b0000000000000000 F
b0000000000000000 G
b0000000000000000 H
b0000000000000000 I
b0000000000000000 J
b0000000000000000 K
b0000000000000000 L
b0000000000000000 M
b0000000000000000 N
b0000000000000000 O
b0000000000000000 P
b0000000000000000 Q
b0000000000000000 R
b0000000000000000 S
b00000000000000000000000000000000 T
b00000000000000000000000000000000 U
1V
1W
b00000000 X
b0000000000000000 Y
#1
0V
#2
b0001111100000001 #
b00000010 /
b00000100 0
b00000010 1
b00000001 2
b00000001 3
b0000000000000001 :
b0001111100000001 ;
b1111 =
b0001 ?
b0000000000000001 C
1V
0W
b00000100 X
#3
0V
#4
b1011000000000101 #
b10 %
0)
b00000000000000000000000000010100 .
b00000100 /
b00000110 0
b00001010 1
b00000101 2
b00000101 3
b0000000000000101 :
b0001000100000000 ;
b0000 =
b0101 ?
b0000000000000101 C
b0000000000000001 S
1V
b00001010 X
#5
0V
#6
b0001000100000000 #
b00 %
1)
b00000000000000000000000000000100 .
b00001010 /
b00001100 0
b00000000 1
b00000000 2
b00000000 3
b0000000000000000 :
b0001111000000000 ;
b0001 =
b0000 ?
b0000000000000000 C
1V
b00001100 X
#7
0V
#8
b1101000100000011 #
b10 %
0)
b00000000000000000000000000010110 .
b00001100 /
b00001110 0
b00000110 1
b00000011 2
b00000011 3
b0000000000000011 :
b0000111100000010 ;
b0011 ?
0B
b0000000000000011 C
1V
b00001110 X
#9
0V
#10
b0001000100000001 #
b00 %
1)
b00000000000000000000000000000100 .
b00001110 /
b00010000 0
b00000010 1
b00000001 2
b00000001 3
b0000000000000001 :
b0001111100000001 ;
b0001 ?
1B
b0000000000000001 C
1V
b00010000 X
#11
0V
#12
b1101000100001010 #
b10 %
0)
b00000000000000000000000000010110 .
b00010000 /
b00010010 0
b00010100 1
b00001010 2
b00001010 3
b0000000000000001 7
b0000000000001010 :
b0001000111111111 ;
b1010 ?
0@
b0000000000001010 C
b0000000000000001 E
1V
b00010100 X
#13
0V
#14
b0001000111111111 #
b00 %
1)
b00000000000000000000000000000100 .
b00010100 /
b00010110 0
b11111110 1
b11111111 2
b11111111 3
b0000000000000010 4
b0000000000000001 5
b0000000000000001 6
b0000000000000001 8
b0000000000000001 9
b1111111111111111 :
b0000000000000000 ;
b0000000000000010 <
b1111 >
b1111 ?
b1111111111111111 C
1V
b00010110 X
#15
0V
#16
b1101000100001100 #
b10 %
0)
b00000000000000000000000000010110 .
b00010110 /
b00011000 0
b00011000 1
b00001100 2
b00001100 3
b0000000000000000 4
b0000000000000000 5
b0000000000000000 6
b1111111111111111 7
b0000000000000000 8
b0000000000000000 9
b0000000000001100 :
b0000111000000010 ;
b0000000000000000 <
b0000 >
b1100 ?
1A
b0000000000001100 C
b1111111111111111 E
1V
b00011000 X
#17
0V
#18
b0000111000000010 #
b00 %
b00000000000000000000000000000011 .
b00011000 /
b00011010 0
b00000100 1
b00000010 2
b00000010 3
b0000000000000000 7
b0000000000000010 :
b1011000000000101 ;
b1110 =
b0010 ?
1@
0A
b0000000000000010 C
1V
b00011010 X
#19
0V
#20
b0001000100000001 #
1)
b00000000000000000000000000000100 .
b00011010 /
b00011100 0
b00000010 1
b00000001 2
b00000001 3
b1111111111111111 4
b1111111111111111 6
b1111111111111111 7
b1111111111111111 9
b0000000000000001 :
b0001111100000001 ;
b1111111111111111 <
b0001 =
b0001 ?
0@
1A
b0000000000000001 C
1V
b00011100 X
#21
0V
#22
b1100000100000011 #
b10 %
0)
b00000000000000000000000000010101 .
b00011100 /
b00011110 0
b00000110 1
b00000011 2
b00000011 3
b0000000000000000 4
b0000000000000000 6
b0000000000000001 7
b0000000000000000 9
b0000000000000011 :
b0000111100000010 ;
b0000000000000000 <
b0011 ?
0A
0B
b0000000000000011 C
b0000000000000001 E
1V
b00011110 X
#23
0V
#24
b0001000111111111 #
b00 %
1)
b00000000000000000000000000000100 .
b00011110 /
b00100000 0
b11111110 1
b11111111 2
b11111111 3
b0000000000000010 4
b0000000000000001 5
b0000000000000001 6
b0000000000000001 8
b0000000000000001 9
b1111111111111111 :
b0000000000000000 ;
b0000000000000010 <
b1111 >
b1111 ?
1B
b1111111111111111 C
1V
b00100000 X
#25
0V
#26
b1100000100000011 #
b10 %
0)
b00000000000000000000000000010101 .
b00100000 /
b00100010 0
b00000110 1
b00000011 2
b00000011 3
b0000000000000000 4
b0000000000000000 5
b0000000000000000 6
b1111111111111111 7
b0000000000000000 8
b0000000000000000 9
b0000000000000011 :
b0000111100000010 ;
b0000000000000000 <
b0000 >
b0011 ?
1A
0B
b0000000000000011 C
b1111111111111111 E
1V
b00100010 X
#27
0V
#28
b0001000100000000 #
b00 %
1)
b00000000000000000000000000000100 .
b00100010 /
b00100100 0
b00000000 1
b00000000 2
b00000000 3
b0000000000000000 :
b0001111000000000 ;
b0000 ?
1B
b0000000000000000 C
1V
b00100100 X
#29
0V
#30
b1100000100010100 #
b10 %
0)
b00000000000000000000000000010101 .
b00100100 /
b00100110 0
b00101000 1
b00010100 2
b00010100 3
b0000000000000000 7
b0000000000010100 :
b0000111000000010 ;
b0001 >
b0100 ?
1@
0A
b0000000000010100 C
b0000000000000000 E
1V
b00101000 X
#31
0V
#32
b0000111000000010 #
b00 %
b00000000000000000000000000000011 .
b00101000 /
b00101010 0
b00000100 1
b00000010 2
b00000010 3
b0000000000000010 :
b1011000000000101 ;
b1110 =
b0000 >
b0010 ?
b0000000000000010 C
1V
b00101010 X
#33
0V
#34
b0001000111111111 #
1)
b00000000000000000000000000000100 .
b00101010 /
b00101100 0
b11111110 1
b11111111 2
b11111111 3
b0000000000000010 4
b0000000000000001 5
b0000000000000001 6
b0000000000000001 8
b0000000000000001 9
b1111111111111111 :
b0000000000000000 ;
b0000000000000010 <
b0001 =
b1111 >
b1111 ?
b1111111111111111 C
1V
b00101100 X
#35
0V
#36
b1110000100000011 #
b10 %
0)
b00000000000000000000000000010111 .
b00101100 /
b00101110 0
b00000110 1
b00000011 2
b00000011 3
b0000000000000000 4
b0000000000000000 5
b0000000000000000 6
b1111111111111111 7
b0000000000000000 8
b0000000000000000 9
b0000000000000011 :
b0000111100000010 ;
b0000000000000000 <
b0000 >
b0011 ?
0@
1A
0B
b0000000000000011 C
b1111111111111111 E
1V
b00101110 X
#37
0V
#38
b0001000100000000 #
b00 %
1)
b00000000000000000000000000000100 .
b00101110 /
b00110000 0
b00000000 1
b00000000 2
b00000000 3
b0000000000000000 :
b0001111000000000 ;
b0000 ?
1B
b0000000000000000 C
1V
b00110000 X
#39
0V
#40
b1110000100000011 #
b10 %
0)
b00000000000000000000000000010111 .
b00110000 /
b00110010 0
b00000110 1
b00000011 2
b00000011 3
b0000000000000000 7
b0000000000000011 :
b0000111100000010 ;
b0011 ?
1@
0A
0B
b0000000000000011 C
b0000000000000000 E
1V
b00110010 X
#41
0V
