hmmm.sv
/* verilator lint_off CASEOVERLAP */
/* verilator lint_off DECLFILENAME */
/* verilator lint_off UNUSEDSIGNAL */

typedef enum {
  HALT,
  NOP,
  READ,
  WRITE,
  SETN,
  LOADR,
  STORER,
  POPR,
  PUSHR,
  LOADN,
  STOREN,
  ADDN,
  ADD,
  COPY,
  SUB,
  NEG,
  MUL,
  DIV,
  MOD,
  JUMPR,
  JUMPN,
  JEQZN,
  JNEZN,
  JGTZN,
  JLTZN,
  CALLN
} instr_t;

typedef enum {
  ALU_ADD,
  ALU_SUB,
  ALU_MUL,
  ALU_DIV,
  ALU_MOD
} aluop_t;


module hmmm (
    input logic clk,
    reset
);
  logic [15:0] Instr;
  logic [1:0] RegSrc, PcSrc;
  logic MemWrite, RegWrite, MemAdrSrc, MemDataSrc;

  aluop_t aluop;
  instr_t instruction_type;


  Controller controller (
      .instr(Instr),
      .aluop(aluop),
      .MemWrite(MemWrite),
      .RegWrite(RegWrite),
      .MemAdrSrc(MemAdrSrc),
      .MemDataSrc(MemDataSrc),
      .RegSrc(RegSrc),
      .PcSrc(PcSrc),
      .instruction_type(instruction_type)
  );

  Datapath datapath (
      .clk(clk),
      .reset(reset),
      .MemWrite(MemWrite),
      .RegWrite(RegWrite),
      .RegSrc(RegSrc),
      .MemAdrSrc(MemAdrSrc),
      .MemDataSrc(MemDataSrc),
      .PcSrc(PcSrc),
      .instruction_type(instruction_type),
      .Instr(Instr)
  );
endmodule

module Memory (
    input logic clk,
    write_en,
    input logic [7:0] instruction_address,
    data_address,
    input logic [15:0] write_data,
    output logic [15:0] instruction_data,
    read_data
);
  initial $readmemb("program.txt", RAM);

  logic [15:0] RAM[255:0];

  always_ff @(posedge clk) if (write_en) RAM[data_address] <= write_data;

  assign instruction_data = RAM[{
    1'b0, instruction_address[7:1]
  }];  // needs to be word-aligned to 2 bytes TODO check
  assign read_data = RAM[data_address];
endmodule

module RegisterFile (
    input logic clk,
    input logic [3:0] address_1,
    address_2,
    address_3,
    input logic write_en_1,
    input logic [15:0] write_data_1,
    output logic [15:0] read_data_1,
    read_data_2,
    read_data_3
);

  logic [15:0] registers[15:0];

  assign read_data_1 = (address_1 != 0) ? registers[address_1] : 16'd0; // be careful on this one, written value doesn't update until next cycle
  assign read_data_2 = (address_2 != 0) ? registers[address_2] : 16'd0;
  assign read_data_3 = (address_3 != 0) ? registers[address_3] : 16'd0;

  always_ff @(posedge clk) if (write_en_1) registers[address_1] <= write_data_1;

endmodule

module Controller (
    input logic [15:0] instr,
    output aluop_t aluop,
    output logic MemWrite,
    RegWrite,
    MemAdrSrc,
    MemDataSrc,
    output logic [1:0] RegSrc,
    PcSrc,
    output instr_t instruction_type
);


  always_comb
    casez (instr)

      // CONTROL_FLOW
      16'b0000_0000_0000_0000: instruction_type = HALT;

      16'b0000_????_0000_0001: instruction_type = READ;  // todo no great way to do in hardware

      16'b0000_????_0000_0010: instruction_type = WRITE;
      16'b0000_????_0000_0011: instruction_type = JUMPR;

      // SETN
      16'b0001_????_????_????: instruction_type = SETN;

      // LOADN
      16'b0010_????_????_????: instruction_type = LOADN;

      // STOREN
      16'b0011_????_????_????: instruction_type = STOREN;


      // MEMORY_R
      16'b0100_????_????_0000: instruction_type = LOADR;
      16'b0100_????_????_0001: instruction_type = STORER;

      16'b0100_????_????_0010: instruction_type = POPR;  // TODO
      16'b0100_????_????_0011: instruction_type = PUSHR;  // TODO

      // ADDN
      16'b0101_????_????_????: instruction_type = ADDN;  // TODO

      // ADD
      16'b0110_????_????_????: instruction_type = ADD;  // TODO
      // 16'b0110_0000_0000_0000: instruction_type = NOP; // add duplicate, handled as default
      16'b0110_????_????_0000: instruction_type = COPY;  // add duplicate

      // SUB
      16'b0111_????_????_????: instruction_type = SUB;  // TODO
      16'b0111_????_0000_????: instruction_type = NEG;  // sub duplicate

      // Mul
      16'b1000_????_????_????: instruction_type = MUL;  // TODO

      // Div
      16'b1001_????_????_????: instruction_type = DIV;  // TODO

      // Mod
      16'b1010_????_????_????: instruction_type = MOD;  // TODO

      // JUMPN_CALLN
      16'b1011_0000_????_????: instruction_type = JUMPN;
      16'b1011_????_????_????: instruction_type = CALLN;


      // Conditional jumps

      16'b1100_????_????_????: instruction_type = JEQZN;  // TODO

      16'b1101_????_????_????: instruction_type = JNEZN;  // TODO

      16'b1110_????_????_????: instruction_type = JGTZN;  // TODO

      16'b1111_????_????_????: instruction_type = JLTZN;  // TODO
      default: begin
        $display("unknown instruction, defaulting to NOP");
        instruction_type = NOP;
      end
    endcase

  // TODO check STOREN
  // TODO check STORER

  // RegSrc:
  //	 00: from immediate
  //	 01: from data memory (data read)
  //	 10: from Pc + 2 (next instruction w/o jump)
  //
  // MemAdrSrc:
  //    0: from immediate
  //    1: from register file (data read 2, rY) // TODO check
  // PcSrc:
  //    00: from PC + 2
  //    10: from PCTarget (immediate)
  //    11: from PCTarget (rX)
  //
  //  MemDataSrc:
  //    0: from ALU result
  //    1: from register file (data read 1, rX) // TODO check
  //


  always_comb begin
    $display("\n");
    MemAdrSrc = 0;  // imm
    MemDataSrc = 0;
    MemWrite = 0;
    PcSrc = 0;  // PC gets PC + 2
    RegSrc = 0;
    RegWrite = 0;
    aluop = ALU_ADD;
    case (instruction_type)
      LOADR: begin
        $display("LOADR");
        // Load register rX with data from the address location held in reg. rY
        MemAdrSrc = 1;  // write to the memory address that is the contents of register rY
        RegSrc = 1;  // pass the data read from memory to the register file
        RegWrite = 1;  // enable write to rx
      end
      WRITE: begin
        $display("WRITE");
        // Print contents of register rX
        // rX is already hard-wired into the first address port of the register file
        // so we will simply print from the corresponding read_data_1 output
      end
      SETN: begin
        $display("SETN");
        // Set register rX equal to the integer N (-128 to +127)
        RegSrc   = 2'b00;  // register file gets write data from immediate
        RegWrite = 1;  // enable write to rx
      end
      LOADN: begin
        $display("LOADN");
        // Load register rX with the contents of memory address N
        MemAdrSrc = 0;  // source memory address from the immediate
        RegSrc    = 1;  // register file gets write data from memory
        RegWrite  = 1;  // enable write to rx
      end
      JUMPN: begin
        // Set program counter to address N
        $display("JUMPN");
        PcSrc = 2'b10;  // next program counter is sourced from the immediate
      end
      JUMPR: begin
        $display("JUMPR");
        //Set program counter to address in rX
        PcSrc = 2'b11;  // next program counter is sourced from the contents of register rX
      end
      CALLN: begin
        $display("CALLN");
        // Copy addr. of next instr. into rX and then jump to mem. addr. N
        PcSrc = 2'b10;  // next program counter is sourced from the immediate
        RegSrc = 2'b10; // register file gets write data from what would have been the next program counter
        RegWrite = 1;  // enable write to rX
      end
      STOREN: begin
        $display("STOREN");
        // Store contents of register rX into memory address N
        MemDataSrc = 1;  // memory gets write data from the contents of register rX
        MemWrite   = 1;  // enable write to memory
      end
      STORER: begin
        $display("STORER");
        // Store contents of register rX into memory address held in reg. rY
        MemAdrSrc  = 1;  // memory gets write data from the contents of register rY
        MemDataSrc = 1;  // memory gets write data from the contents of register rX
        MemWrite   = 1;  // enable write to memory
      end

      ADD: aluop = ALU_ADD;
    endcase
  end



endmodule

module Datapath (
    input logic clk,
    reset,
    input logic MemWrite,
    RegWrite,
    MemAdrSrc,
    MemDataSrc,
    input logic [1:0] PcSrc,
    RegSrc,
    input instr_t instruction_type,
    output logic [15:0] Instr
);

  logic [7:0] Pc, PcPlus2, PcNext, PcTarget, Imm, MemDataAddress;

  logic [15:0]
      Result,
      ALUResult,
      SrcA,
      rf_read_data_1,
      rf_read_data_2,
      rf_read_data_3,
      mem_read_data,
      mem_write_data;

  logic [3:0] rX, rY, rZ;


  //assign opcode = Instr[15:12];
  assign rX = Instr[11:8];
  assign rY = Instr[7:4];
  assign rZ = Instr[3:0];

  assign Imm = Instr[7:0];


  // PC logic
  assign PcTarget = PcSrc[0] ? rf_read_data_1[7:0] * 2 : Imm * 2;  // todo check

  assign PcPlus2 = Pc + 2;


  always_comb
    if (reset) PcNext = 0;
    else if (PcSrc[1]) PcNext = PcTarget;
    else PcNext = PcPlus2;  // word alignment is 2 bytes

  always_ff @(posedge clk) Pc <= PcNext;

  always_ff @(posedge clk) begin
    $display("instruction_address: %h", Pc);
    $display("instruction: %h", Instr);

    // cheat to handle write
    if (instruction_type == WRITE) $display("write: %b", rf_read_data_1);
    else if (instruction_type == HALT) begin
      $display("halt");
      // dump regs
      for (int i = 0; i < 15; i++) begin
        $display("reg[%d]: %h", i, rf.registers[i]);
      end
      $display("\n");
      // dump memory
      for (int i = 0; i < 255; i++) begin
        $display("mem[%d]: %h", i, mem.RAM[i]);
      end

      $finish;
    end
  end



  assign MemDataAddress = MemAdrSrc ? rf_read_data_2[7:0] : Imm;



  assign ALUResult = 16'dx;
  assign mem_write_data = MemDataSrc ? rf_read_data_1 : ALUResult;  // TODO check


  // Memory logic
  Memory mem (
      .clk(clk),
      .write_en(MemWrite),
      .instruction_address(Pc),
      .data_address(MemDataAddress),
      .write_data(mem_write_data),
      .instruction_data(Instr),
      .read_data(mem_read_data)
  );


  always_comb
    case (RegSrc)
      2'b00:   Result = {8'b0, Imm};
      2'b01:   Result = mem_read_data;
      2'b10:   Result = {8'b0, PcPlus2};
      default: Result = 16'bx;
    endcase


  // REGISTER FILE logic
  RegisterFile rf (
      .clk(clk),
      .address_1(rX),
      .address_2(rY),
      .address_3(rZ),
      .write_en_1(RegWrite),
      .write_data_1(Result),
      .read_data_1(rf_read_data_1),
      .read_data_2(rf_read_data_2),
      .read_data_3(rf_read_data_3)
  );
  // TODO EXTEND

  // ALU logic
  //ALU alu(.ALUOp(ALUOp), .Zero(Zero), .SrcA(SrcA), .SrcB(SrcB), .ALUResult(ALUResult));


endmodule

module ALU (
    input aluop_t ALUOp,
    input logic [15:0] SrcA,
    SrcB,
    output logic [15:0] ALUResult,
    output logic Zero,
    Sign
);

  always_comb
    case (ALUOp)
      ALU_ADD: ALUResult = SrcA + SrcB;
      ALU_SUB: ALUResult = SrcA + ~SrcB + 1;
      ALU_MUL: ALUResult = SrcA * SrcB;
      ALU_DIV: ALUResult = SrcA / SrcB;
      ALU_MOD: ALUResult = SrcA % SrcB;
      default: ALUResult = 16'dx;
    endcase

  assign Zero = (ALUResult == 0);
  assign Sign = ALUResult[15];

endmodule

waveform.vcd
$version Generated by VerilatedVcd $end
$timescale 1ps $end

 $scope module TOP $end
  $var wire  1 L clk $end
  $var wire  1 M reset $end
  $scope module hmmm $end
   $var wire 16 # Instr [15:0] $end
   $var wire  1 ( MemAdrSrc $end
   $var wire  1 ) MemDataSrc $end
   $var wire  1 & MemWrite $end
   $var wire  2 % PcSrc [1:0] $end
   $var wire  2 $ RegSrc [1:0] $end
   $var wire  1 ' RegWrite $end
   $var wire 32 * aluop [31:0] $end
   $var wire  1 L clk $end
   $var wire 32 + instruction_type [31:0] $end
   $var wire  1 M reset $end
   $scope module controller $end
    $var wire  1 ( MemAdrSrc $end
    $var wire  1 ) MemDataSrc $end
    $var wire  1 & MemWrite $end
    $var wire  2 % PcSrc [1:0] $end
    $var wire  2 $ RegSrc [1:0] $end
    $var wire  1 ' RegWrite $end
    $var wire 32 * aluop [31:0] $end
    $var wire 16 # instr [15:0] $end
    $var wire 32 + instruction_type [31:0] $end
   $upscope $end
   $scope module datapath $end
    $var wire 16 O ALUResult [15:0] $end
    $var wire  8 / Imm [7:0] $end
    $var wire 16 # Instr [15:0] $end
    $var wire  1 ( MemAdrSrc $end
    $var wire  8 0 MemDataAddress [7:0] $end
    $var wire  1 ) MemDataSrc $end
    $var wire  1 & MemWrite $end
    $var wire  8 , Pc [7:0] $end
    $var wire  8 N PcNext [7:0] $end
    $var wire  8 - PcPlus2 [7:0] $end
    $var wire  2 % PcSrc [1:0] $end
    $var wire  8 . PcTarget [7:0] $end
    $var wire  2 $ RegSrc [1:0] $end
    $var wire  1 ' RegWrite $end
    $var wire 16 1 Result [15:0] $end
    $var wire 16 P SrcA [15:0] $end
    $var wire  1 L clk $end
    $var wire 32 + instruction_type [31:0] $end
    $var wire 16 5 mem_read_data [15:0] $end
    $var wire 16 6 mem_write_data [15:0] $end
    $var wire  4 7 rX [3:0] $end
    $var wire  4 8 rY [3:0] $end
    $var wire  4 9 rZ [3:0] $end
    $var wire  1 M reset $end
    $var wire 16 2 rf_read_data_1 [15:0] $end
    $var wire 16 3 rf_read_data_2 [15:0] $end
    $var wire 16 4 rf_read_data_3 [15:0] $end
    $scope module mem $end
     $var wire  1 L clk $end
     $var wire  8 0 data_address [7:0] $end
     $var wire  8 , instruction_address [7:0] $end
     $var wire 16 # instruction_data [15:0] $end
     $var wire 16 5 read_data [15:0] $end
     $var wire 16 6 write_data [15:0] $end
     $var wire  1 & write_en $end
    $upscope $end
    $scope module rf $end
     $var wire  4 7 address_1 [3:0] $end
     $var wire  4 8 address_2 [3:0] $end
     $var wire  4 9 address_3 [3:0] $end
     $var wire  1 L clk $end
     $var wire 16 2 read_data_1 [15:0] $end
     $var wire 16 3 read_data_2 [15:0] $end
     $var wire 16 4 read_data_3 [15:0] $end
     $var wire 16 : registers[0] [15:0] $end
     $var wire 16 D registers[10] [15:0] $end
     $var wire 16 E registers[11] [15:0] $end
     $var wire 16 F registers[12] [15:0] $end
     $var wire 16 G registers[13] [15:0] $end
     $var wire 16 H registers[14] [15:0] $end
     $var wire 16 I registers[15] [15:0] $end
     $var wire 16 ; registers[1] [15:0] $end
     $var wire 16 < registers[2] [15:0] $end
     $var wire 16 = registers[3] [15:0] $end
     $var wire 16 > registers[4] [15:0] $end
     $var wire 16 ? registers[5] [15:0] $end
     $var wire 16 @ registers[6] [15:0] $end
     $var wire 16 A registers[7] [15:0] $end
     $var wire 16 B registers[8] [15:0] $end
     $var wire 16 C registers[9] [15:0] $end
     $var wire 16 1 write_data_1 [15:0] $end
     $var wire  1 ' write_en_1 $end
    $upscope $end
    $scope module unnamedblk1 $end
     $var wire 32 J i [31:0] $end
    $upscope $end
    $scope module unnamedblk2 $end
     $var wire 32 K i [31:0] $end
    $upscope $end
   $upscope $end
  $upscope $end
 $upscope $end
$enddefinitions $end


#0
b0001000100101010 #
b00 $
b00 %
0&
1'
1(
0)
b00000000000000000000000000000000 *
b00000000000000000000000000000100 +
b00000000 ,
b00000010 -
b01010100 .
b00101010 /
b00000000 0
b0000000000101010 1
b0000000000000000 2
b0000000000000000 3
b0000000000000000 4
b0001000100101010 5
b0000000000000000 6
b0001 7
b0010 8
b1010 9
b0000000000000000 :
b0000000000000000 ;
b0000000000000000 <
b0000000000000000 =
b0000000000000000 >
b0000000000000000 ?
b0000000000000000 @
b0000000000000000 A
b0000000000000000 B
b0000000000000000 C
b0000000000000000 D
b0000000000000000 E
b0000000000000000 F
b0000000000000000 G
b0000000000000000 H
b0000000000000000 I
b00000000000000000000000000000000 J
b00000000000000000000000000000000 K
1L
1M
b00000000 N
b0000000000000000 O
b0000000000000000 P
#1
0L
#2
b0011000101100100 #
1&
0'
0(
1)
b00000000000000000000000000001010 +
b00000010 ,
b00000100 -
b11001000 .
b01100100 /
b01100100 0
b0000000001100100 1
b0000000000101010 2
b0000000000000000 5
b0000000000101010 6
b0110 8
b0100 9
b0000000000101010 ;
1L
0M
b00000100 N
#3
0L
#4
b0100000100010001 #
1(
b00000000000000000000000000000110 +
b00000100 ,
b00000110 -
b00100010 .
b00010001 /
b00101010 0
b0000000000010001 1
b0000000000101010 3
b0000000000101010 4
b0001 8
b0001 9
1L
b00000110 N
#5
0L
#6
b0001001000000110 #
0&
1'
0)
b00000000000000000000000000000100 +
b00000110 ,
b00001000 -
b00001100 .
b00000110 /
b00000000 0
b0000000000000110 1
b0000000000000000 2
b0000000000000000 3
b0000000000000000 4
b0001000100101010 5
b0000000000000000 6
b0010 7
b0000 8
b0110 9
1L
b00001000 N
#7
0L
#8
b0000001000000011 #
b11 %
0'
0(
b00000000000000000000000000010011 +
b00001000 ,
b00001010 -
b00000011 /
b00000011 0
b0000000000000011 1
b0000000000000110 2
b0001001000000110 5
b0011 9
b0000000000000110 <
1L
b00001100 N
#9
0L
#10
b1011000000001000 #
b10 %
b00000000000000000000000000010100 +
b00001100 ,
b00001110 -
b00010000 .
b00001000 /
b00001000 0
b0000000000001000 1
b0000000000000000 2
b0000000000000010 5
b0000 7
b1000 9
1L
b00010000 N
#11
0L
#12
b0000000000000010 #
b00 %
1(
b00000000000000000000000000000011 +
b00010000 ,
b00010010 -
b00000100 .
b00000010 /
b00000000 0
b0000000000000010 1
b0000000000000110 4
b0001000100101010 5
b0010 9
1L
b00010010 N
#13
0L
#14
b0010001101100100 #
b01 $
1'
0(
b00000000000000000000000000001001 +
b00010010 ,
b00010100 -
b11001000 .
b01100100 /
b01100100 0
b0000000000101010 1
b0000000000000000 4
b0000000000101010 5
b0011 7
b0110 8
b0100 9
1L
b00010100 N
#15
0L
#16
b0100010000010000 #
1(
b00000000000000000000000000000101 +
b00010100 ,
b00010110 -
b00100000 .
b00010000 /
b00101010 0
b0000000000101010 3
b0100 7
b0001 8
b0000 9
b0000000000101010 =
1L
b00010110 N
#17
0L
#18
b0000001100000010 #
b00 $
0'
b00000000000000000000000000000011 +
b00010110 ,
b00011000 -
b00000100 .
b00000010 /
b00000000 0
b0000000000000010 1
b0000000000101010 2
b0000000000000000 3
b0000000000000110 4
b0001000100101010 5
b0011 7
b0000 8
b0010 9
b0000000000101010 >
1L
b00011000 N
#19
0L
#20
b0000010000000010 #
b00011000 ,
b00011010 -
b0100 7
1L
b00011010 N
#21
0L
#22
b1011010100001111 #
b10 $
b10 %
1'
0(
b00000000000000000000000000011001 +
b00011010 ,
b00011100 -
b00011110 .
b00001111 /
b00001111 0
b0000000000011100 1
b0000000000000000 2
b0000000000000000 4
b0000010100000010 5
b0101 7
b1111 9
1L
b00011110 N
#23
0L
#24
b0000010100000010 #
b00 $
b00 %
0'
1(
b00000000000000000000000000000011 +
b00011110 ,
b00100000 -
b00000100 .
b00000010 /
b00000000 0
b0000000000000010 1
b0000000000011100 2
b0000000000000110 4
b0001000100101010 5
b0010 9
b0000000000011100 ?
1L
b00100000 N
#25
0L
#26
b0000010100000011 #
b11 %
0(
b00000000000000000000000000010011 +
b00100000 ,
b00100010 -
b00111000 .
b00000011 /
b00000011 0
b0000000000000011 1
b0000000000101010 4
b0001001000000110 5
b0011 9
1L
b00111000 N
#27
0L
#28
b0000000000000000 #
b00 %
b00000000000000000000000000000000 +
b00111000 ,
b00111010 -
b00000000 .
b00000000 /
b00000000 0
b0000000000000000 1
b0000000000000000 2
b0000000000000000 4
b0001000100101010 5
b0000 7
b0000 9
1L
b00111010 N
#29
0L
#30
b00111010 ,
b00111100 -
b00000000000000000000000000001111 J
b00000000000000000000000011111111 K
1L
b00111100 N
