hmmm.sv
/* verilator lint_off CASEOVERLAP */
/* verilator lint_off DECLFILENAME */
/* verilator lint_off UNUSEDSIGNAL */

typedef enum {
  HALT,
  NOP,
  READ,
  WRITE,
  SETN,
  LOADR,
  STORER,
  POPR,
  PUSHR,
  LOADN,
  STOREN,
  ADDN,
  ADD,
  SUB,
  MUL,
  DIV,
  MOD,
  JUMPR,
  JUMPN,
  JEQZN,
  JNEZN,
  JGTZN,
  JLTZN,
  CALLN
} instr_t;

typedef enum {
  ALU_ADD,
  ALU_MUL,
  ALU_DIV,
  ALU_MOD
} aluop_t;


module hmmm (
    input logic clk,
    reset
);
  logic [15:0] Instr;
  logic MemWrite, RegWrite, RegSrc, MemAdrSrc, PcSrc;

  aluop_t aluop;
  instr_t instruction_type;


  Controller controller (
      .instr(Instr),
      .aluop(aluop),
      .MemWrite(MemWrite),
      .RegWrite(RegWrite),
      .MemAdrSrc(MemAdrSrc),
      .RegSrc(RegSrc),
      .PcSrc(PcSrc),
      .instruction_type(instruction_type)
  );
  Datapath datapath (
      .clk(clk),
      .reset(reset),
      .MemWrite(MemWrite),
      .RegWrite(RegWrite),
      .RegSrc(RegSrc),
      .MemAdrSrc(MemAdrSrc),
      .PcSrc(PcSrc),
      .instruction_type(instruction_type),
      .Instr(Instr)
  );
endmodule
module Memory (
    input logic clk,
    write_en,
    input logic [7:0] instruction_address,
    data_address,
    input logic [15:0] write_data,
    output logic [15:0] instruction_data,
    read_data
);
  initial $readmemb("program.txt", RAM);

  logic [15:0] RAM[255:0];

  always_ff @(posedge clk) if (write_en) RAM[data_address] <= write_data;

  assign instruction_data = RAM[{
    1'b0, instruction_address[7:1]
  }];  // needs to be word-aligned to 2 bytes TODO check
  assign read_data = RAM[data_address];
endmodule

module RegisterFile (
    input logic clk,
    input logic [3:0] address_1,
    address_2,
    address_3,
    input logic write_en_1,
    input logic [15:0] write_data_1,
    output logic [15:0] read_data_1, read_data_2,
    read_data_3
);

  logic [15:0] registers[15:0];

  assign read_data_1 = (address_1 != 0) ? registers[address_1] : 16'd0; // be careful on this one, written value doesn't update until next cycle
  assign read_data_2 = (address_2 != 0) ? registers[address_2] : 16'd0;
  assign read_data_3 = (address_3 != 0) ? registers[address_3] : 16'd0;

  always_ff @(posedge clk) if (write_en_1) registers[address_1] <= write_data_1;

endmodule

module Controller (
    input logic [15:0] instr,
    output aluop_t aluop,
    output MemWrite,
    RegWrite, RegSrc, MemAdrSrc, PcSrc,
    output instr_t instruction_type
);


  always_comb
    casez (instr)

      // CONTROL_FLOW
      16'b0000_0000_0000_0000: instruction_type = HALT;
      // TODO not really any good way to do read
      16'b0000_????_0000_0001: instruction_type = READ;
      16'b0000_????_0000_0010: instruction_type = WRITE;  // This was hacked, TODO make better
      16'b0000_????_0000_0011: instruction_type = JUMPR;  // TODO

      // SETN
      16'b0001_????_????_????: instruction_type = SETN; 

      // LOADN
      16'b0010_????_????_????: instruction_type = LOADN;

      // STOREN
      16'b0011_????_????_????: instruction_type = STOREN;  // TODO


      // MEMORY_R
      16'b0100_????_????_0000: instruction_type = LOADR;  
      16'b0100_????_????_0001: instruction_type = STORER;  // TODO
      16'b0100_????_????_0010: instruction_type = POPR;  // TODO
      16'b0100_????_????_0011: instruction_type = PUSHR;  // TODO

      // ADDN
      16'b0101_????_????_????: instruction_type = ADDN;  // TODO

      // ADD
      16'b0110_????_????_????: instruction_type = ADD;  // TODO
      // 16'b0110_0000_0000_0000: instruction_type = NOP; // add duplicate
      // 16'b0110_????_????_0000: instruction_type = COPY; // add duplicate

      // SUB
      16'b0111_????_????_????:
      instruction_type = SUB;  // just an add with inverted second source // TODO
      // 16'b0111_????_0000_????: instruction_type = NEG; // sub duplicate

      // Mul
      16'b1000_????_????_????: instruction_type = MUL;  // TODO

      // Div
      16'b1001_????_????_????: instruction_type = DIV;  // TODO

      // Mod
      16'b1010_????_????_????: instruction_type = MOD;  // TODO

      // JUMPN_CALLN
      16'b1011_0000_????_????: instruction_type = JUMPN;  // instr[11:8]  // TODO
      16'b1011_????_0000_0000: instruction_type = CALLN;  // TODO


      // Conditional jumps

      16'b1100_????_????_????: instruction_type = JEQZN;  // TODO

      16'b1101_????_????_????: instruction_type = JNEZN;  // TODO

      16'b1110_????_????_????: instruction_type = JGTZN;  // TODO

      16'b1111_????_????_????: instruction_type = JLTZN;  // TODO
      default: instruction_type = NOP;
    endcase


    // RegSrc:
    //	  0: from immediate
    //	  1: from data memory (data read)
    //
    // MemAdrSrc:
    //    0: from immediate
    //    1: from register file (data read 2)
    // PcSrc:
    //    0: from PC + 2
    //    1: from PCTarget (right now, just immediate)


  always_comb begin
    $display("\n");
    MemWrite = 0;
    RegWrite = 0;
    RegSrc = 0;
    MemAdrSrc = 0; // imm
    PcSrc = 0;  // PC gets PC + 2
    aluop = ALU_ADD;
    case (instruction_type)
      LOADR: begin
	$display("LOADR");
        //MemWrite = 0;
        RegWrite = 1;
	RegSrc = 1;
	MemAdrSrc = 1;
      end
      WRITE: begin
	$display("WRITE");
        //MemWrite = 0;
        //RegWrite = 0;
	MemAdrSrc = 1;
      end
      SETN: begin
	$display("SETN");
	RegWrite = 1;
	RegSrc = 0; // implied but fine TODO
	MemAdrSrc = 1;
      end
      LOADN: begin
	$display("LOADN");
	RegWrite = 1;
	RegSrc = 1;
	MemAdrSrc = 0;
      end
      JUMPN: begin
	$display("JUMPN");
	PcSrc = 1;
      end
      CALLN: begin
	$display("CALLN");
	// TODO
      end

      ADD: aluop = ALU_ADD;
    endcase
  end



endmodule

module Datapath (
    input logic clk,
    reset,
    input logic MemWrite,
    RegWrite, RegSrc, MemAdrSrc, PcSrc,
    input instr_t instruction_type,
    output logic [15:0] Instr
);

  logic [7:0] Pc, PcTarget, Imm, MemDataAddress;

  logic [15:0] Result, SrcA, rf_read_data_1, rf_read_data_2, rf_read_data_3, mem_read_data;

  logic [3:0] rX, rY, rZ;


  //assign opcode = Instr[15:12];
  assign rX = Instr[11:8];
  assign rY = Instr[7:4];
  assign rZ = Instr[3:0];

  assign Imm = Instr[7:0];


  // PC logic
  assign PcTarget = Imm *2;

  always_ff @(posedge clk, posedge reset)
    if (reset) Pc <= 0;
    else if (PcSrc) Pc <= PcTarget;
    else Pc <= Pc + 2;  // word alignment is 2 bytes

  always_ff @(posedge clk)
  begin
    $display("instruction_address: %h", Pc);
    $display("instruction: %h", Instr);

    // cheat to handle write
    if (instruction_type == WRITE) $display("write: %b", rf_read_data_1);
    else if (instruction_type == HALT) begin
      $display("halt");
      $finish;
    end
  end



  assign MemDataAddress = MemAdrSrc ? rf_read_data_2[7:0] : Imm;


  // Memory logic
  Memory mem (
      .clk(clk),
      .write_en(0),
      .instruction_address(Pc),
      .data_address(MemDataAddress),
      .write_data(16'dx),
      .instruction_data(Instr),
      .read_data(mem_read_data)
  );

  assign Result = RegSrc ? mem_read_data : {8'b0, Imm};


  // REGISTER FILE logic
  RegisterFile rf (
      .clk(clk),
      .address_1(rX),
      .address_2(rY),
      .address_3(rZ),
      .write_en_1(RegWrite),
      .write_data_1(Result),
      .read_data_1(rf_read_data_1),
      .read_data_2(rf_read_data_2),
      .read_data_3(rf_read_data_3)
  );
  // TODO EXTEND

  // ALU logic
  //ALU alu(.ALUOp(ALUOp), .Zero(Zero), .SrcA(SrcA), .SrcB(SrcB), .ALUResult(ALUResult));





endmodule

module ALU (
    input logic Zero,
    input aluop_t ALUOp,
    input logic [15:0] SrcA,
    SrcB,
    output logic [15:0] ALUResult
);

endmodule

waveform.vcd
$version Generated by VerilatedVcd $end
$timescale 1ps $end

 $scope module TOP $end
  $var wire  1 F clk $end
  $var wire  1 G reset $end
  $scope module hmmm $end
   $var wire 16 9 Instr [15:0] $end
   $var wire  1 < MemAdrSrc $end
   $var wire  1 H MemWrite $end
   $var wire  1 = PcSrc $end
   $var wire  1 ; RegSrc $end
   $var wire  1 : RegWrite $end
   $var wire 32 > aluop [31:0] $end
   $var wire  1 F clk $end
   $var wire 32 ? instruction_type [31:0] $end
   $var wire  1 G reset $end
   $scope module controller $end
    $var wire  1 < MemAdrSrc $end
    $var wire  1 H MemWrite $end
    $var wire  1 = PcSrc $end
    $var wire  1 ; RegSrc $end
    $var wire  1 : RegWrite $end
    $var wire 32 > aluop [31:0] $end
    $var wire 16 9 instr [15:0] $end
    $var wire 32 ? instruction_type [31:0] $end
   $upscope $end
   $scope module datapath $end
    $var wire  8 B Imm [7:0] $end
    $var wire 16 9 Instr [15:0] $end
    $var wire  1 < MemAdrSrc $end
    $var wire  8 3 MemDataAddress [7:0] $end
    $var wire  1 H MemWrite $end
    $var wire  8 @ Pc [7:0] $end
    $var wire  1 = PcSrc $end
    $var wire  8 A PcTarget [7:0] $end
    $var wire  1 ; RegSrc $end
    $var wire  1 : RegWrite $end
    $var wire 16 4 Result [15:0] $end
    $var wire 16 I SrcA [15:0] $end
    $var wire  1 F clk $end
    $var wire 32 ? instruction_type [31:0] $end
    $var wire 16 8 mem_read_data [15:0] $end
    $var wire  4 C rX [3:0] $end
    $var wire  4 D rY [3:0] $end
    $var wire  4 E rZ [3:0] $end
    $var wire  1 G reset $end
    $var wire 16 5 rf_read_data_1 [15:0] $end
    $var wire 16 6 rf_read_data_2 [15:0] $end
    $var wire 16 7 rf_read_data_3 [15:0] $end
    $scope module mem $end
     $var wire  1 F clk $end
     $var wire  8 3 data_address [7:0] $end
     $var wire  8 @ instruction_address [7:0] $end
     $var wire 16 9 instruction_data [15:0] $end
     $var wire 16 8 read_data [15:0] $end
     $var wire 16 J write_data [15:0] $end
     $var wire  1 H write_en $end
    $upscope $end
    $scope module rf $end
     $var wire  4 C address_1 [3:0] $end
     $var wire  4 D address_2 [3:0] $end
     $var wire  4 E address_3 [3:0] $end
     $var wire  1 F clk $end
     $var wire 16 5 read_data_1 [15:0] $end
     $var wire 16 6 read_data_2 [15:0] $end
     $var wire 16 7 read_data_3 [15:0] $end
     $var wire 16 # registers[0] [15:0] $end
     $var wire 16 - registers[10] [15:0] $end
     $var wire 16 . registers[11] [15:0] $end
     $var wire 16 / registers[12] [15:0] $end
     $var wire 16 0 registers[13] [15:0] $end
     $var wire 16 1 registers[14] [15:0] $end
     $var wire 16 2 registers[15] [15:0] $end
     $var wire 16 $ registers[1] [15:0] $end
     $var wire 16 % registers[2] [15:0] $end
     $var wire 16 & registers[3] [15:0] $end
     $var wire 16 ' registers[4] [15:0] $end
     $var wire 16 ( registers[5] [15:0] $end
     $var wire 16 ) registers[6] [15:0] $end
     $var wire 16 * registers[7] [15:0] $end
     $var wire 16 + registers[8] [15:0] $end
     $var wire 16 , registers[9] [15:0] $end
     $var wire 16 4 write_data_1 [15:0] $end
     $var wire  1 : write_en_1 $end
    $upscope $end
   $upscope $end
  $upscope $end
 $upscope $end
$enddefinitions $end


#0
b0000000000000000 #
b0000000000000000 $
b0000000000000000 %
b0000000000000000 &
b0000000000000000 '
b0000000000000000 (
b0000000000000000 )
b0000000000000000 *
b0000000000000000 +
b0000000000000000 ,
b0000000000000000 -
b0000000000000000 .
b0000000000000000 /
b0000000000000000 0
b0000000000000000 1
b0000000000000000 2
b00000000 3
b0100000100000000 4
b0000000000000000 5
b0000000000000000 6
b0000000000000000 7
b0100000100000000 8
b0100000100000000 9
1:
1;
1<
0=
b00000000000000000000000000000000 >
b00000000000000000000000000000101 ?
b00000000 @
b00000000 A
b00000000 B
b0001 C
b0000 D
b0000 E
1F
1G
0H
b0000000000000000 I
b0000000000000000 J
#1
0F
#2
b0100000100000000 $
b0000000000000010 4
b0001001000000010 9
0;
b00000000000000000000000000000100 ?
b00000010 @
b00000100 A
b00000010 B
b0010 C
b0010 E
1F
0G
#3
0F
#4
b0000000000000010 %
b0000000000000010 5
b0000000000000010 7
b0000001000000010 9
0:
b00000000000000000000000000000011 ?
b00000100 @
1F
#5
0F
#6
b0000000000000011 4
b0000000000000000 5
b0000000000000000 7
b0001001100000011 9
1:
b00000000000000000000000000000100 ?
b00000110 @
b00000110 A
b00000011 B
b0011 C
b0011 E
1F
#7
0F
#8
b0000000000000011 &
b0000000000000010 4
b0000000000000011 5
b0000000000000010 7
b0000001100000010 9
0:
b00000000000000000000000000000011 ?
b00001000 @
b00000100 A
b00000010 B
b0010 E
1F
#9
0F
#10
b0000000000000100 4
b0000000000000000 5
b0000000000000000 7
b0001010000000100 9
1:
b00000000000000000000000000000100 ?
b00001010 @
b00001000 A
b00000100 B
b0100 C
b0100 E
1F
#11
0F
#12
b0000000000000100 '
b0000000000000010 4
b0000000000000100 5
b0000000000000010 7
b0000010000000010 9
0:
b00000000000000000000000000000011 ?
b00001100 @
b00000100 A
b00000010 B
b0010 E
1F
#13
0F
#14
b00000001 3
b0001001000000010 4
b0000000000000000 5
b0100000100000000 7
b0001001000000010 8
b0010010100000001 9
1:
1;
0<
b00000000000000000000000000001001 ?
b00001110 @
b00000010 A
b00000001 B
b0101 C
b0001 E
1F
#15
0F
#16
b0001001000000010 (
b00000000 3
b0000000000000010 4
b0001001000000010 5
b0000000000000010 7
b0100000100000000 8
b0000010100000010 9
0:
0;
1<
b00000000000000000000000000000011 ?
b00010000 @
b00000100 A
b00000010 B
b0010 E
1F
#17
0F
#18
b00001001 3
b0000000000001001 4
b0000000000000000 5
b0000000000000000 7
b1011000000001001 8
b1011000000001001 9
0<
1=
b00000000000000000000000000010010 ?
b00010010 @
b00010010 A
b00001001 B
b0000 C
b1001 E
1F
