hmmm.sv
/* verilator lint_off CASEOVERLAP */
/* verilator lint_off DECLFILENAME */
/* verilator lint_off UNUSEDSIGNAL */
/* verilator lint_off CASEINCOMPLETE */

typedef enum {
  HALT,
  NOP,
  READ,
  WRITE,
  SETN,
  LOADR,
  STORER,
  POPR,
  PUSHR,
  LOADN,
  STOREN,
  ADDN,
  ADD,
  COPY,
  SUB,
  NEG,
  MUL,
  DIV,
  MOD,
  JUMPR,
  JUMPN,
  JEQZN,
  JNEZN,
  JGTZN,
  JLTZN,
  CALLN
} instr_t;

typedef enum {
  ALU_ADD,
  ALU_SUB,
  ALU_MUL,
  ALU_DIV,
  ALU_MOD
} alu_op_t;


module hmmm (
    input logic clk,
    reset
);
  logic [15:0] Instr;
  logic [1:0] RegSrcX, PcSrc, MemAdrSrc, ALUSrcB;
  logic MemWrite, RegWriteX, RegWriteY, MemDataSrc, ALUSrcA;

  alu_op_t alu_op;
  instr_t  instruction_type;


  Controller controller (
      .instr(Instr),
      .alu_op(alu_op),
      .ALUSrcA(ALUSrcA),
      .ALUSrcB(ALUSrcB),
      .MemWrite(MemWrite),
      .RegWriteX(RegWriteX),
      .RegSrcX(RegSrcX),
      .RegWriteY(RegWriteY),
      .MemAdrSrc(MemAdrSrc),
      .MemDataSrc(MemDataSrc),
      .PcSrc(PcSrc),
      .instruction_type(instruction_type)
  );

  Datapath datapath (
      .clk(clk),
      .reset(reset),
      .MemWrite(MemWrite),
      .RegWriteX(RegWriteX),
      .RegSrcX(RegSrcX),
      .RegWriteY(RegWriteY),
      .MemAdrSrc(MemAdrSrc),
      .MemDataSrc(MemDataSrc),
      .PcSrc(PcSrc),
      .alu_op(alu_op),
      .ALUSrcA(ALUSrcA),
      .ALUSrcB(ALUSrcB),
      .instruction_type(instruction_type),
      .Instr(Instr)
  );
endmodule

module Memory (
    input logic clk,
    write_en,
    input logic [7:0] instruction_address,
    data_address,
    input logic [15:0] write_data,
    output logic [15:0] instruction_data,
    read_data
);
  initial $readmemb("program.txt", RAM);

  logic [15:0] RAM[255:0];

  always_ff @(posedge clk) if (write_en) RAM[data_address] <= write_data;

  assign instruction_data = RAM[{
    1'b0, instruction_address[7:1]
  }];  // needs to be word-aligned to 2 bytes TODO check
  assign read_data = RAM[data_address];
endmodule

module RegisterFile (
    input logic clk,
    input logic [3:0] address_1,
    address_2,
    address_3,
    input logic write_en_1,
    write_en_2,
    input logic [15:0] write_data_1,
    write_data_2,
    output logic [15:0] read_data_1,
    read_data_2,
    read_data_3
);

  // TODO pretty sure we are allocating flops for r0 needlessly
  logic [15:0] registers[15:0];

  assign read_data_1 = (address_1 != 0) ? registers[address_1] : 16'd0; // be careful on this one, written value doesn't update until next cycle
  assign read_data_2 = (address_2 != 0) ? registers[address_2] : 16'd0;
  assign read_data_3 = (address_3 != 0) ? registers[address_3] : 16'd0;

  always_ff @(posedge clk) begin
    if (write_en_1 & write_en_2 & (address_1 == address_2))
      $display(
          "WARNING: write to same register in same cycle. Second write channel takes priority."
      );
    if (write_en_1) registers[address_1] = write_data_1;
    if (write_en_2) registers[address_2] = write_data_2;
  end
endmodule

module Controller (
    input logic [15:0] instr,
    output alu_op_t alu_op,
    output logic MemWrite,
    RegWriteX,
    RegWriteY,
    MemDataSrc,
    ALUSrcA,
    output logic [1:0] RegSrcX,
    ALUSrcB,
    MemAdrSrc,
    PcSrc,
    output instr_t instruction_type
);


  always_comb
    casez (instr)

      // CONTROL_FLOW
      16'b0000_0000_0000_0000: instruction_type = HALT;

      16'b0000_????_0000_0001: instruction_type = READ;  // todo no great way to do in hardware

      16'b0000_????_0000_0010: instruction_type = WRITE;
      16'b0000_????_0000_0011: instruction_type = JUMPR;

      // SETN
      16'b0001_????_????_????: instruction_type = SETN;

      // LOADN
      16'b0010_????_????_????: instruction_type = LOADN;

      // STOREN
      16'b0011_????_????_????: instruction_type = STOREN;


      // MEMORY_R
      16'b0100_????_????_0000: instruction_type = LOADR;
      16'b0100_????_????_0001: instruction_type = STORER;

      16'b0100_????_????_0010: instruction_type = POPR;  // TODO
      16'b0100_????_????_0011: instruction_type = PUSHR;  // TODO

      // ADDN
      16'b0101_????_????_????: instruction_type = ADDN;  // TODO

      // ADD
      16'b0110_????_????_????: instruction_type = ADD;  // TODO
      // 16'b0110_0000_0000_0000: instruction_type = NOP; // add duplicate, handled as default
      16'b0110_????_????_0000: instruction_type = COPY;  // add duplicate

      // SUB
      16'b0111_????_????_????: instruction_type = SUB;  // TODO
      16'b0111_????_0000_????: instruction_type = NEG;  // sub duplicate

      // Mul
      16'b1000_????_????_????: instruction_type = MUL;  // TODO

      // Div
      16'b1001_????_????_????: instruction_type = DIV;  // TODO

      // Mod
      16'b1010_????_????_????: instruction_type = MOD;  // TODO

      // JUMPN_CALLN
      16'b1011_0000_????_????: instruction_type = JUMPN;
      16'b1011_????_????_????: instruction_type = CALLN;


      // Conditional jumps

      16'b1100_????_????_????: instruction_type = JEQZN;  // TODO

      16'b1101_????_????_????: instruction_type = JNEZN;  // TODO

      16'b1110_????_????_????: instruction_type = JGTZN;  // TODO

      16'b1111_????_????_????: instruction_type = JLTZN;  // TODO
      default: begin
        $display("unknown instruction, defaulting to NOP");
        instruction_type = NOP;
      end
    endcase

  // RegSrcX:
  //	 00: from immediate
  //	 01: from data memory (data read)
  //	 10: from Pc + 2 (next instruction w/o jump)
  //	 11: from ALU result
  //
  //
  // MemAdrSrc:
  //   00: from immediate
  //   01: from register file (data read 2, rY) 
  //   10: from alu_result
  //
  // PcSrc:
  //    00: from PC + 2
  //    10: from PCTarget (immediate)
  //    11: from PCTarget (rX)
  //
  //  MemDataSrc: 
  //    0: from ALU result
  //    1: from register file (data read 1, rX) 
  //
  //  AluSrcA:
  //    0: from register file (data read 2, rY)
  //    1: from register file (data read 1, rX)
  //
  //  AluSrcB: 
  //    00: from register file (data read 3, rZ)
  //    01: from immediate
  //    10: from 0
  //    11: from 1


  always_comb begin
    // defaults
    MemAdrSrc = 2'b0;  // memory sources from immediate
    MemDataSrc = 0;  // memory gets write data from ALU result
    MemWrite = 0;  // disable write to memory
    PcSrc = 2'b00;  // PC gets PC + 2
    RegSrcX = 2'b00;  // register file gets write data from immediate
    RegWriteX = 0;  // disable write to register file
    alu_op = ALU_ADD;  // default ALU operation is ADD
    ALUSrcA = 0;  // default ALU source A is the contents of register rX
    ALUSrcB = 2'b00;  // default ALU source B is the contents of register rY

    $display("\n");
    case (instruction_type)
      LOADR: begin
        $display("LOADR");
        // Load register rX with data from the address location held in reg. rY
        MemAdrSrc = 2'b1;  // write to the memory address that is the contents of register rY
        RegSrcX   = 2'b01;  // pass the data read from memory to the register file
        RegWriteX = 1;  // enable write to rx
      end
      READ: begin
        $display("READ");
        // emulator, read from stdin, processor, read from 16 bit input (presumed to be hooked up to serial transfer peripheral)
        // Ideally, should stall the processor until the input is ready.
        // TODO 
        $display("WARNING: READ unimplemented.");
      end
      WRITE: begin
        $display("WRITE");
        // Print contents of register rX
        // rX is already hard-wired into the first address port of the register file
        // so we will simply print from the corresponding read_data_1 output
      end
      SETN: begin
        $display("SETN");
        // Set register rX equal to the integer N (-128 to +127)
        RegSrcX   = 2'b00;  // register file gets write data from immediate
        RegWriteX = 1;  // enable write to rx
      end
      LOADN: begin
        $display("LOADN");
        // Load register rX with the contents of memory address N
        MemAdrSrc = 2'b0;  // source memory address from the immediate
        RegSrcX   = 2'b01;  // register file gets write data from memory
        RegWriteX = 1;  // enable write to rx
      end
      JUMPN: begin
        // Set program counter to address N
        $display("JUMPN");
        PcSrc = 2'b10;  // next program counter is sourced from the immediate
      end
      JUMPR: begin
        $display("JUMPR");
        //Set program counter to address in rX
        PcSrc = 2'b11;  // next program counter is sourced from the contents of register rX
      end
      JEQZN: begin
        $display("JEQZN");
        // If the contents of register rX is zero, set program counter to address N
        PcSrc   = 2'b10;  // next program counter is sourced from the immediate // CHECK
        // We will mul rx * 1 so we can use the comparison logic in the ALU on rX
        alu_op  = ALU_MUL;  // ALU operation is ADD
        ALUSrcA = 1;  // default ALU source A is the contents of register rX
        ALUSrcB = 2'b10;  // default ALU source B is 0 (to enable comparison with 0)

      end
      JNEZN: begin
        $display("JNEZN");
        // If the contents of register rX is not zero, set program counter to address N
        PcSrc   = 2'b10;  // next program counter is sourced from the immediate // CHECK
        // We will mul rx * 1 so we can use the comparison logic in the ALU on rX
        alu_op  = ALU_MUL;  // ALU operation is ADD
        ALUSrcA = 1;  // default ALU source A is the contents of register rX
        ALUSrcB = 2'b10;  // default ALU source B is 0 (to enable comparison with 0)
      end
      JGTZN: begin
        $display("JGTZN");
        // If the contents of register rX is greater than zero, set program counter to address N
        PcSrc   = 2'b10;  // next program counter is sourced from the immediate // CHECK
        // We will mul rx * 1 so we can use the comparison logic in the ALU on rX
        alu_op  = ALU_MUL;  // ALU operation is ADD
        ALUSrcA = 1;  // default ALU source A is the contents of register rX
        ALUSrcB = 2'b10;  // default ALU source B is 0 (to enable comparison with 0)
      end
      JLTZN: begin
        $display("JLTZN");
        // If the contents of register rX is less than zero, set program counter to address N
        PcSrc   = 2'b10;  // next program counter is sourced from the immediate // CHECK
        // We will mul rx * 1 so we can use the comparison logic in the ALU on rX
        alu_op  = ALU_MUL;  // ALU operation is ADD
        ALUSrcA = 1;  // default ALU source A is the contents of register rX
        ALUSrcB = 2'b10;  // default ALU source B is 0 (to enable comparison with 0)
      end
      CALLN: begin
        $display("CALLN");
        // Copy addr. of next instr. into rX and then jump to mem. addr. N
        PcSrc = 2'b10;  // next program counter is sourced from the immediate
        RegSrcX = 2'b10; // register file gets write data from what would have been the next program counter
        RegWriteX = 1;  // enable write to rX
      end
      STOREN: begin
        $display("STOREN");
        // Store contents of register rX into memory address N
        MemDataSrc = 1;  // memory gets write data from the contents of register rX
        MemWrite   = 1;  // enable write to memory
      end
      STORER: begin
        $display("STORER");
        // Store contents of register rX into memory address held in reg. rY
        MemAdrSrc  = 2'b1;  // memory gets write data from the contents of register rY
        MemDataSrc = 1;  // memory gets write data from the contents of register rX
        MemWrite   = 1;  // enable write to memory
      end
      POPR: begin
        $display("POPR");
        // Load contents of register rX from stack pointed to by register rY: rY -= 1; rX = memory[rY]
        ALUSrcA = 0;  // rY
        ALUSrcB = 2'b11;  // 1
        alu_op = ALU_SUB;  // sub
        MemAdrSrc = 2'b10;  // get the value from the memory address corresponding to the alu_result
        RegWriteX = 1;  // enable write to rX
        RegSrcX = 2'b01;  // rx gets write data from memory
        RegWriteY = 1;  // enable write to rY (default from alu_result)
      end
      PUSHR: begin
        $display("PUSHR");
        // Store contents of register rX onto stack pointed to by register rY: memory[rY] = rX; rY += 1
        ALUSrcA = 0;  // rY
        ALUSrcB = 2'b11;  // 1
        alu_op = ALU_ADD;  // add
        MemWrite = 1;  // enable write to memory
        MemDataSrc = 1;  // memory gets write data from the contents of register rX
        MemAdrSrc = 2'b01;  // read from memory address that is the value of rY
        RegWriteY = 1;  // enable write to rY (default from alu_result)
      end
      ADD, COPY, NOP: begin
        case (instruction_type)
          ADD: $display("ADD");
          COPY:
          $display(
              "COPY"
          );  // COPY is the case of ADD where sources b from r0, which is hard-wired to 0
          NOP:
          $display(
              "NOP"
          );  // NOP is the case of ADD where a, b, and result are all from/to r0, which is hard-wired to 0
        endcase
        alu_op = ALU_ADD;
        ALUSrcA = 0;  // default ALU source A is the contents of register rY
        ALUSrcB = 2'b00;  // default ALU source B is the contents of register rZ
        RegSrcX = 2'b11;  // register file gets write data from the ALU result
        RegWriteX = 1;  // enable write to rx
      end
      ADDN: begin  // Copy is a duplicate of ADD which always gets 
        $display("ADDN");
        alu_op = ALU_ADD;
        ALUSrcA = 1;  // default ALU source A is the contents of register rX
        ALUSrcB = 2'b01;  // ALU source B is the immediate
        RegSrcX = 2'b11;  // register file gets write data from the ALU result
        RegWriteX = 1;  // enable write to rx
      end
      SUB, NEG: begin
        case (instruction_type)
          SUB: $display("SUB");
          NEG:
          $display(
              "NEG"
          );  // NEG is the case of SUB where source a is taken from r0, which is hard-wired to 0
        endcase
        alu_op = ALU_SUB;
        ALUSrcA = 0;  // default ALU source A is the contents of register rY
        ALUSrcB = 2'b00;  // default ALU source B is the contents of register rZ
        RegSrcX = 2'b11;  // register file gets write data from the ALU result
        RegWriteX = 1;  // enable write to rx
      end
      MUL: begin
        $display("MUL");
        alu_op = ALU_MUL;
        ALUSrcA = 0;  // default ALU source A is the contents of register rY
        ALUSrcB = 2'b00;  // default ALU source B is the contents of register rZ
        RegSrcX = 2'b11;  // register file gets write data from the ALU result
        RegWriteX = 1;  // enable write to rx
      end
      DIV: begin
        $display("DIV");
        alu_op = ALU_DIV;
        ALUSrcA = 0;  // default ALU source A is the contents of register rY
        ALUSrcB = 2'b00;  // default ALU source B is the contents of register rZ
        RegSrcX = 2'b11;  // register file gets write data from the ALU result
        RegWriteX = 1;  // enable write to rx
      end
      MOD: begin
        $display("MOD");
        alu_op = ALU_MOD;
        ALUSrcA = 0;  // default ALU source A is the contents of register rY
        ALUSrcB = 2'b00;  // default ALU source B is the contents of register rZ
        RegSrcX = 2'b11;  // register file gets write data from the ALU result
        RegWriteX = 1;  // enable write to rx
      end
    endcase
  end



endmodule

module Datapath (
    input logic clk,
    reset,
    input logic MemWrite,
    RegWriteX,
    RegWriteY,
    MemDataSrc,
    ALUSrcA,
    input logic [1:0] PcSrc,
    ALUSrcB,
    RegSrcX,
    MemAdrSrc,
    input instr_t instruction_type,
    input alu_op_t alu_op,
    output logic [15:0] Instr
);

  // ==============  Internal Signals ============== 


  logic [7:0] Pc, PcPlus2, PcNext, PcTarget, Imm, mem_data_address;

  logic [15:0]
      result,
      alu_result,
      alu_src_a,
      alu_src_b,
      rf_read_data_1,
      rf_read_data_2,
      rf_read_data_3,
      rf_write_data_1,
      rf_write_data_2,
      mem_read_data,
      mem_write_data;

  logic [3:0] rX, rY, rZ;

  assign rX  = Instr[11:8];
  assign rY  = Instr[7:4];
  assign rZ  = Instr[3:0];

  assign Imm = Instr[7:0];

  logic zero, sign;

  // ============== PC logic ============== 
  always_ff @(posedge clk) Pc <= PcNext;



  logic take_jump;

  always_comb
    case (instruction_type)
      JEQZN:   take_jump = zero;
      JNEZN:   take_jump = ~zero;
      JGTZN:   take_jump = ~sign & ~zero;
      JLTZN:   take_jump = sign;
      JUMPR:   take_jump = 1;
      JUMPN:   take_jump = 1;
      default: take_jump = 1;
    endcase

  always_comb
    if (reset) PcNext = 0;
    else if (PcSrc[1] & take_jump) PcNext = PcTarget;
    else PcNext = PcPlus2;  // word alignment is 2 bytes

  assign PcTarget = PcSrc[0] ? rf_read_data_1[7:0] : Imm << 1;  // todo check
  assign PcPlus2  = Pc + 2;


  // cheat to handle status prints, write and halt

  always_ff @(posedge clk) begin
    $display("Instruction number: %d", Pc / 2);
    $display("instruction: %h", Instr);

    if (instruction_type == WRITE) $display("write: %b", rf_read_data_1);
    else if (instruction_type == HALT) begin
      $display("halt");

      // dump registers
      for (int i = 0; i < 15; i++) begin
        $display("reg[%d]: %h", i, rf.registers[i]);
      end
      $display("\n");
      // dump memory
      for (int i = 0; i < 255; i++) begin
        $display("mem[%d]: %h", i, mem.RAM[i]);
      end
      // done
      $finish;
    end
  end


  // ============== Memory logic ============== 
  Memory mem (
      .clk(clk),
      .write_en(MemWrite),
      .instruction_address(Pc),
      .data_address(mem_data_address),
      .write_data(mem_write_data),
      .instruction_data(Instr),
      .read_data(mem_read_data)
  );

  always_comb
    case (MemAdrSrc)
      2'b00: mem_data_address = Imm;
      2'b01: mem_data_address = rf_read_data_2[7:0];
      2'b10: mem_data_address = alu_result[7:0];
    endcase

  assign mem_write_data = MemDataSrc ? rf_read_data_1 : alu_result;

  logic [15:0] imm_ext;
  assign imm_ext = Imm[7] ? {8'b11111111, Imm} : {8'b0, Imm};

  always_comb
    case (RegSrcX)
      2'b00: rf_write_data_1 = imm_ext;
      2'b01: rf_write_data_1 = mem_read_data;
      2'b10: rf_write_data_1 = {8'b0, PcPlus2};
      2'b11: rf_write_data_1 = alu_result;
    endcase

  assign rf_write_data_2 = alu_result;

  // ============== REGISTER FILE logic ============== 
  RegisterFile rf (
      .clk(clk),
      .address_1(rX),
      .address_2(rY),
      .address_3(rZ),
      .write_en_1(RegWriteX),
      .write_en_2(RegWriteY),
      .write_data_1(rf_write_data_1),
      .write_data_2(rf_write_data_2),
      .read_data_1(rf_read_data_1),
      .read_data_2(rf_read_data_2),
      .read_data_3(rf_read_data_3)
  );

  // ============= ALU logic ============== 

  ALU alu (
      .alu_op(alu_op),
      .zero(zero),
      .sign(sign),
      .src_a(alu_src_a),
      .src_b(alu_src_b),
      .alu_result(alu_result)
  );

  assign alu_src_a = ALUSrcA ? rf_read_data_1 : rf_read_data_2;

  always_comb
    case (ALUSrcB)
      2'b0:  alu_src_b = rf_read_data_3;
      2'b1:  alu_src_b = imm_ext;
      2'b10: alu_src_b = 0;
      2'b11: alu_src_b = 1;
    endcase
endmodule

module ALU (
    input alu_op_t alu_op,
    input logic [15:0] src_a,
    src_b,
    output logic [15:0] alu_result,
    output logic zero,
    sign
);

  always_comb
    case (alu_op)
      ALU_ADD: alu_result = src_a + src_b;
      ALU_SUB: alu_result = src_a - src_b;
      ALU_MUL: alu_result = src_a * src_b;
      ALU_DIV: alu_result = src_a / src_b;  // todo check div by 0
      ALU_MOD: alu_result = src_a % src_b;
    endcase

  assign zero = (alu_result == 0);
  assign sign = alu_result[15];

endmodule

waveform.vcd
$version Generated by VerilatedVcd $end
$timescale 1ps $end

 $scope module TOP $end
  $var wire  1 V clk $end
  $var wire  1 W reset $end
  $scope module hmmm $end
   $var wire  1 , ALUSrcA $end
   $var wire  2 ' ALUSrcB [1:0] $end
   $var wire 16 # Instr [15:0] $end
   $var wire  2 & MemAdrSrc [1:0] $end
   $var wire  1 + MemDataSrc $end
   $var wire  1 ( MemWrite $end
   $var wire  2 % PcSrc [1:0] $end
   $var wire  2 $ RegSrcX [1:0] $end
   $var wire  1 ) RegWriteX $end
   $var wire  1 * RegWriteY $end
   $var wire 32 - alu_op [31:0] $end
   $var wire  1 V clk $end
   $var wire 32 . instruction_type [31:0] $end
   $var wire  1 W reset $end
   $scope module controller $end
    $var wire  1 , ALUSrcA $end
    $var wire  2 ' ALUSrcB [1:0] $end
    $var wire  2 & MemAdrSrc [1:0] $end
    $var wire  1 + MemDataSrc $end
    $var wire  1 ( MemWrite $end
    $var wire  2 % PcSrc [1:0] $end
    $var wire  2 $ RegSrcX [1:0] $end
    $var wire  1 ) RegWriteX $end
    $var wire  1 * RegWriteY $end
    $var wire 32 - alu_op [31:0] $end
    $var wire 16 # instr [15:0] $end
    $var wire 32 . instruction_type [31:0] $end
   $upscope $end
   $scope module datapath $end
    $var wire  1 , ALUSrcA $end
    $var wire  2 ' ALUSrcB [1:0] $end
    $var wire  8 2 Imm [7:0] $end
    $var wire 16 # Instr [15:0] $end
    $var wire  2 & MemAdrSrc [1:0] $end
    $var wire  1 + MemDataSrc $end
    $var wire  1 ( MemWrite $end
    $var wire  8 / Pc [7:0] $end
    $var wire  8 X PcNext [7:0] $end
    $var wire  8 0 PcPlus2 [7:0] $end
    $var wire  2 % PcSrc [1:0] $end
    $var wire  8 1 PcTarget [7:0] $end
    $var wire  2 $ RegSrcX [1:0] $end
    $var wire  1 ) RegWriteX $end
    $var wire  1 * RegWriteY $end
    $var wire 32 - alu_op [31:0] $end
    $var wire 16 4 alu_result [15:0] $end
    $var wire 16 5 alu_src_a [15:0] $end
    $var wire 16 6 alu_src_b [15:0] $end
    $var wire  1 V clk $end
    $var wire 16 C imm_ext [15:0] $end
    $var wire 32 . instruction_type [31:0] $end
    $var wire  8 3 mem_data_address [7:0] $end
    $var wire 16 ; mem_read_data [15:0] $end
    $var wire 16 < mem_write_data [15:0] $end
    $var wire  4 = rX [3:0] $end
    $var wire  4 > rY [3:0] $end
    $var wire  4 ? rZ [3:0] $end
    $var wire  1 W reset $end
    $var wire 16 Y result [15:0] $end
    $var wire 16 7 rf_read_data_1 [15:0] $end
    $var wire 16 8 rf_read_data_2 [15:0] $end
    $var wire 16 9 rf_read_data_3 [15:0] $end
    $var wire 16 : rf_write_data_1 [15:0] $end
    $var wire 16 4 rf_write_data_2 [15:0] $end
    $var wire  1 A sign $end
    $var wire  1 B take_jump $end
    $var wire  1 @ zero $end
    $scope module alu $end
     $var wire 32 - alu_op [31:0] $end
     $var wire 16 4 alu_result [15:0] $end
     $var wire  1 A sign $end
     $var wire 16 5 src_a [15:0] $end
     $var wire 16 6 src_b [15:0] $end
     $var wire  1 @ zero $end
    $upscope $end
    $scope module mem $end
     $var wire  1 V clk $end
     $var wire  8 3 data_address [7:0] $end
     $var wire  8 / instruction_address [7:0] $end
     $var wire 16 # instruction_data [15:0] $end
     $var wire 16 ; read_data [15:0] $end
     $var wire 16 < write_data [15:0] $end
     $var wire  1 ( write_en $end
    $upscope $end
    $scope module rf $end
     $var wire  4 = address_1 [3:0] $end
     $var wire  4 > address_2 [3:0] $end
     $var wire  4 ? address_3 [3:0] $end
     $var wire  1 V clk $end
     $var wire 16 7 read_data_1 [15:0] $end
     $var wire 16 8 read_data_2 [15:0] $end
     $var wire 16 9 read_data_3 [15:0] $end
     $var wire 16 D registers[0] [15:0] $end
     $var wire 16 N registers[10] [15:0] $end
     $var wire 16 O registers[11] [15:0] $end
     $var wire 16 P registers[12] [15:0] $end
     $var wire 16 Q registers[13] [15:0] $end
     $var wire 16 R registers[14] [15:0] $end
     $var wire 16 S registers[15] [15:0] $end
     $var wire 16 E registers[1] [15:0] $end
     $var wire 16 F registers[2] [15:0] $end
     $var wire 16 G registers[3] [15:0] $end
     $var wire 16 H registers[4] [15:0] $end
     $var wire 16 I registers[5] [15:0] $end
     $var wire 16 J registers[6] [15:0] $end
     $var wire 16 K registers[7] [15:0] $end
     $var wire 16 L registers[8] [15:0] $end
     $var wire 16 M registers[9] [15:0] $end
     $var wire 16 : write_data_1 [15:0] $end
     $var wire 16 4 write_data_2 [15:0] $end
     $var wire  1 ) write_en_1 $end
     $var wire  1 * write_en_2 $end
    $upscope $end
    $scope module unnamedblk1 $end
     $var wire 32 T i [31:0] $end
    $upscope $end
    $scope module unnamedblk2 $end
     $var wire 32 U i [31:0] $end
    $upscope $end
   $upscope $end
  $upscope $end
 $upscope $end
$enddefinitions $end


#0
b0001000100000001 #
b00 $
b00 %
b00 &
b00 '
0(
1)
0*
0+
0,
b00000000000000000000000000000000 -
b00000000000000000000000000000100 .
b00000000 /
b00000010 0
b00000010 1
b00000001 2
b00000001 3
b0000000000000000 4
b0000000000000000 5
b0000000000000000 6
b0000000000000000 7
b0000000000000000 8
b0000000000000000 9
b0000000000000001 :
b0001001000000010 ;
b0000000000000000 <
b0001 =
b0000 >
b0001 ?
1@
0A
1B
b0000000000000001 C
b0000000000000000 D
b0000000000000000 E
b0000000000000000 F
b0000000000000000 G
b0000000000000000 H
b0000000000000000 I
b0000000000000000 J
b0000000000000000 K
b0000000000000000 L
b0000000000000000 M
b0000000000000000 N
b0000000000000000 O
b0000000000000000 P
b0000000000000000 Q
b0000000000000000 R
b0000000000000000 S
b00000000000000000000000000000000 T
b00000000000000000000000000000000 U
1V
1W
b00000000 X
b0000000000000000 Y
#1
0V
#2
b0001001000000010 #
b00000010 /
b00000100 0
b00000100 1
b00000010 2
b00000010 3
b0000000000000010 :
b0001001100000011 ;
b0010 =
b0010 ?
b0000000000000010 C
b0000000000000001 E
1V
0W
b00000100 X
#3
0V
#4
b0001001100000011 #
b00000100 /
b00000110 0
b00000110 1
b00000011 2
b00000011 3
b0000000000000011 :
b0001010100101000 ;
b0011 =
b0011 ?
b0000000000000011 C
b0000000000000010 F
1V
b00000110 X
#5
0V
#6
b0001010100101000 #
b00000110 /
b00001000 0
b01010000 1
b00101000 2
b00101000 3
b0000000000000010 4
b0000000000000010 5
b0000000000000010 8
b0000000000101000 :
b0000000000000000 ;
b0000000000000010 <
b0101 =
b0010 >
b1000 ?
0@
b0000000000101000 C
b0000000000000011 G
1V
b00001000 X
#7
0V
#8
b1011010000001001 #
b10 $
b10 %
b00000000000000000000000000011001 .
b00001000 /
b00001010 0
b00010010 1
b00001001 2
b00001001 3
b0000000000000000 4
b0000000000000000 5
b0000000000000000 8
b0000000000001010 :
b0100000101010011 ;
b0000000000000000 <
b0100 =
b0000 >
b1001 ?
1@
b0000000000001001 C
b0000000000101000 I
1V
b00010010 X
#9
0V
#10
b0100000101010011 #
b00 $
b00 %
b01 &
b11 '
1(
0)
1*
1+
b00000000000000000000000000001000 .
b00010010 /
b00010100 0
b10100110 1
b01010011 2
b00101000 3
b0000000000101001 4
b0000000000101000 5
b0000000000000001 6
b0000000000000001 7
b0000000000101000 8
b0000000000000011 9
b0000000001010011 :
b0000000000000000 ;
b0000000000000001 <
b0001 =
b0101 >
b0011 ?
0@
b0000000001010011 C
b0000000000001010 H
1V
b00010100 X
#11
0V
#12
b0100001001010011 #
b00010100 /
b00010110 0
b00101001 3
b0000000000101010 4
b0000000000101001 5
b0000000000000010 7
b0000000000101001 8
b0000000000000010 <
b0010 =
b0000000000101001 I
1V
b00010110 X
#13
0V
#14
b0100001101010011 #
b00010110 /
b00011000 0
b00101010 3
b0000000000101011 4
b0000000000101010 5
b0000000000000011 7
b0000000000101010 8
b0000000000000011 <
b0011 =
b0000000000101010 I
1V
b00011000 X
#15
0V
#16
b0101000100101010 #
b11 $
b00 &
b01 '
0(
1)
0+
1,
b00000000000000000000000000001011 .
b00011000 /
b00011010 0
b01010100 1
b00101010 2
b0000000000000001 5
b0000000000101010 6
b0000000000000001 7
b0000000000000010 8
b0000000000000000 9
b0000000000101011 :
b0000000000000011 ;
b0000000000101011 <
b0001 =
b0010 >
b1010 ?
b0000000000101010 C
b0000000000101011 I
1V
b00011010 X
#17
0V
#18
b0101001000101010 #
b00011010 /
b00011100 0
b0000000001010101 4
b0000000000101011 5
b0000000000101011 7
b0000000000101011 8
b0000000001010101 :
b0000000001010101 <
b0010 =
b0000000000101011 E
b0000000000101011 F
1V
b00011100 X
#19
0V
#20
b0101001100101010 #
b00011100 /
b00011110 0
b0000000000101101 4
b0000000000000011 5
b0000000000000011 7
b0000000001010101 8
b0000000000101101 :
b0000000000101101 <
b0011 =
b0000000001010101 F
1V
b00011110 X
#21
0V
#22
b0100001101010010 #
b01 $
b10 &
b11 '
0,
b00000000000000000000000000000001 -
b00000000000000000000000000000111 .
b00011110 /
b00100000 0
b10100100 1
b01010010 2
b0000000000101010 4
b0000000000101011 5
b0000000000000001 6
b0000000000101101 7
b0000000000101011 8
b0000000000101101 9
b0000000000000011 :
b0000000000101010 <
b0101 >
b0010 ?
b0000000001010010 C
b0000000000101101 F
b0000000000101101 G
1V
b00100000 X
#23
0V
#24
b0100001001010010 #
b00100000 /
b00100010 0
b00101001 3
b0000000000101001 4
b0000000000101010 5
b0000000000101010 8
b0000000000000010 :
b0000000000000010 ;
b0000000000101001 <
b0010 =
b0000000000000011 G
b0000000000101010 I
1V
b00100010 X
#25
0V
#26
b0100000101010010 #
b00100010 /
b00100100 0
b00101000 3
b0000000000101000 4
b0000000000101001 5
b0000000000101011 7
b0000000000101001 8
b0000000000000010 9
b0000000000000001 :
b0000000000000001 ;
b0000000000101000 <
b0001 =
b0000000000000010 F
b0000000000101001 I
1V
b00100100 X
#27
0V
#28
b0000010000000011 #
b00 $
b11 %
b00 &
b00 '
0)
b00000000000000000000000000000000 -
b00000000000000000000000000010011 .
b00100100 /
b00100110 0
b00001010 1
b00000011 2
b00000011 3
b0000000000000011 4
b0000000000000000 5
b0000000000000011 6
b0000000000001010 7
b0000000000000000 8
b0000000000000011 9
b0000000000000011 :
b0001010100101000 ;
b0000000000000011 <
b0100 =
b0000 >
b0011 ?
b0000000000000011 C
b0000000000000001 E
b0000000000101000 I
1V
b00001010 X
#29
0V
#30
b0000000100000010 #
b00 %
b00000000000000000000000000000011 .
b00001010 /
b00001100 0
b00000100 1
b00000010 2
b00000010 3
b0000000000000010 4
b0000000000000010 6
b0000000000000001 7
b0000000000000010 9
b0000000000000010 :
b0001001100000011 ;
b0000000000000010 <
b0001 =
b0010 ?
b0000000000000010 C
b0000000000000011 D
1V
b00001100 X
#31
0V
#32
b0000001000000010 #
b00001100 /
b00001110 0
b0000000000000010 7
b0010 =
b0000000000000010 D
1V
b00001110 X
#33
0V
#34
b0000001100000010 #
b00001110 /
b00010000 0
b0000000000000011 7
b0011 =
1V
b00010000 X
#35
0V
#36
b0000000000000000 #
b00000000000000000000000000000000 .
b00010000 /
b00010010 0
b00000000 1
b00000000 2
b00000000 3
b0000000000000000 4
b0000000000000000 6
b0000000000000000 7
b0000000000000000 9
b0000000000000000 :
b0001000100000001 ;
b0000000000000000 <
b0000 =
b0000 ?
1@
b0000000000000000 C
1V
b00010010 X
#37
0V
#38
b0100000101010011 #
b01 &
b11 '
1(
1+
b00000000000000000000000000001000 .
b00010010 /
b00010100 0
b10100110 1
b01010011 2
b00101000 3
b0000000000101001 4
b0000000000101000 5
b0000000000000001 6
b0000000000000001 7
b0000000000101000 8
b0000000000000011 9
b0000000001010011 :
b0000000000000001 ;
b0000000000000001 <
b0001 =
b0101 >
b0011 ?
0@
b0000000001010011 C
b0000000000000000 D
b00000000000000000000000000001111 T
b00000000000000000000000011111111 U
1V
b00010100 X
